{"eventGroup":{"eventGroupId":"84240","displayGroupId":"7","name":"MLB","offerCategories":[{"offerCategoryId":493,"name":"Game Lines","offerSubcategoryDescriptors":[{"subcategoryId":4519,"name":"Game","offerSubcategory":{"name":"Game","subcategoryId":4519,"componentId":210,"tags":["SGP"],"offers":[[{"providerOfferId":"2_80190092","eventId":"32385261","eventGroupId":"84240","label":"Run Line","isSuspended":false,"isOpen":true,"offerSubcategoryId":4519,"isSubcategoryFeatured":true,"betOfferTypeId":1,"providerCriterionId":"2_0","outcomes":[{"providerOutcomeId":"0HC80190092P150_3","providerId":2,"providerOfferId":"2_80190092","label":"MIA Marlins","oddsAmerican":"-142","oddsDecimal":1.70422536,"oddsDecimalDisplay":"1.70","oddsFractional":"50/71","line":1.5,"participant":"MIA Marlins","participantType":"Team","main":true,"sortOrder":1499,"tags":["MainPointLine","SGP"],"participants":[{"id":"29953","name":"MIA Marlins","type":"Team"}]},{"providerOutcomeId":"0HC80190092N150_1","providerId":2,"providerOfferId":"2_80190092","label":"TB Rays","oddsAmerican":"\u002B120","oddsDecimal":2.2,"oddsDecimalDisplay":"2.20","oddsFractional":"6/5","line":-1.5,"participant":"TB Rays","participantType":"Team","main":true,"sortOrder":1501,"tags":["MainPointLine","SGP"],"participants":[{"id":"29880","name":"TB Rays","type":"Team"}]}],"offerSequence":0,"source":"5","displayGroupId":"7","main":true,"tags":["SGP","YourBetEligible","Cashout","FeaturedSubcategory","Default","PrimaryMarket"]},{"providerOfferId":"3_80190092","eventId":"32385261","eventGroupId":"84240","label":"Total","isSuspended":false,"isOpen":true,"offerSubcategoryId":4519,"isSubcategoryFeatured":true,"betOfferTypeId":6,"providerCriterionId":"3_0","outcomes":[{"providerOutcomeId":"0OU80190092O950_1","providerId":2,"providerOfferId":"3_80190092","label":"Over","oddsAmerican":"\u002B100","oddsDecimal":2,"oddsDecimalDisplay":"2.00","oddsFractional":"1/1","line":9.5,"participant":"","participantType":"Unknown","main":true,"sortOrder":9500,"tags":["ProgressiveParlayTeamEligible","MainPointLine","SGP"]},{"providerOutcomeId":"0OU80190092U950_3","providerId":2,"providerOfferId":"3_80190092","label":"Under","oddsAmerican":"-120","oddsDecimal":1.83333334,"oddsDecimalDisplay":"1.83","oddsFractional":"5/6","line":9.5,"participant":"","participantType":"Unknown","main":true,"sortOrder":9502,"tags":["ProgressiveParlayTeamEligible","MainPointLine","SGP"]}],"offerSequence":0,"source":"5","displayGroupId":"7","main":true,"tags":["ProgressiveParlayTeamEligible","SGP","YourBetEligible","Cashout","FeaturedSubcategory","Default","PrimaryMarket"]},{"providerOfferId":"-1379028575","eventId":"32385261","eventGroupId":"84240","isSuspended":false,"isOpen":false,"offerSubcategoryId":4519,"isSubcategoryFeatured":false,"betOfferTypeId":2,"outcomes":[{"providerId":0,"oddsDecimal":0,"hidden":true,"main":true,"sortOrder":0},{"providerId":0,"oddsDecimal":0,"hidden":true,"main":true,"sortOrder":0}],"offerSequence":0,"main":true}],[{"providerOfferId":"2_80190102","eventId":"32385265","eventGroupId":"84240","label":"Run Line","isSuspended":false,"isOpen":true,"offerSubcategoryId":4519,"isSubcategoryFeatured":true,"betOfferTypeId":1,"providerCriterionId":"2_0","outcomes":[{"providerOutcomeId":"0HC80190102N150_3","providerId":2,"providerOfferId":"2_80190102","label":"PHI Phillies","oddsAmerican":"\u002B114","oddsDecimal":2.14,"oddsDecimalDisplay":"2.14","oddsFractional":"57/50","line":-1.5,"participant":"PHI Phillies","participantType":"Team","main":true,"sortOrder":-1501,"tags":["MainPointLine","SGP"],"participants":[{"id":"29857","name":"PHI Phillies","type":"Team"}]},{"providerOutcomeId":"0HC80190102P150_1","providerId":2,"providerOfferId":"2_80190102","label":"PIT Pirates","oddsAmerican":"-135","oddsDecimal":1.74074075,"oddsDecimalDisplay":"1.74","oddsFractional":"20/27","line":1.5,"participant":"PIT Pirates","participantType":"Team","main":true,"sortOrder":-1499,"tags":["MainPointLine","SGP"],"participants":[{"id":"29924","name":"PIT Pirates","type":"Team"}]}],"offerSequence":0,"source":"5","displayGroupId":"7","main":true,"tags":["SGP","YourBetEligible","Cashout","FeaturedSubcategory","Default","PrimaryMarket"]},{"providerOfferId":"3_80190102","eventId":"32385265","eventGroupId":"84240","label":"Total","isSuspended":false,"isOpen":true,"offerSubcategoryId":4519,"isSubcategoryFeatured":true,"betOfferTypeId":6,"providerCriterionId":"3_0","outcomes":[{"providerOutcomeId":"0OU80190102O900_1","providerId":2,"providerOfferId":"3_80190102","label":"Over","oddsAmerican":"-102","oddsDecimal":1.98039216,"oddsDecimalDisplay":"1.98","oddsFractional":"50/51","line":9,"participant":"","participantType":"Unknown","main":true,"sortOrder":9000,"tags":["ProgressiveParlayTeamEligible","MainPointLine","SGP"]},{"providerOutcomeId":"0OU80190102U900_3","providerId":2,"providerOfferId":"3_80190102","label":"Under","oddsAmerican":"-118","oddsDecimal":1.84745763,"oddsDecimalDisplay":"1.84","oddsFractional":"50/59","line":9,"participant":"","participantType":"Unknown","main":true,"sortOrder":9002,"tags":["ProgressiveParlayTeamEligible","MainPointLine","SGP"]}],"offerSequence":0,"source":"5","displayGroupId":"7","main":true,"tags":["ProgressiveParlayTeamEligible","SGP","YourBetEligible","Cashout","FeaturedSubcategory","Default","PrimaryMarket"]},{"providerOfferId":"1_80190102","eventId":"32385265","eventGroupId":"84240","label":"Moneyline","isSuspended":false,"isOpen":true,"offerSubcategoryId":4519,"isSubcategoryFeatured":true,"betOfferTypeId":2,"providerCriterionId":"1_0","outcomes":[{"providerOutcomeId":"0ML80190102_3","providerId":2,"providerOfferId":"1_80190102","label":"PHI Phillies","oddsAmerican":"-142","oddsDecimal":1.70422536,"oddsDecimalDisplay":"1.70","oddsFractional":"50/71","participant":"PHI Phillies","participantType":"Team","main":true,"sortOrder":4251935,"tags":["SGP"],"participants":[{"id":"29857","name":"PHI Phillies","type":"Team"}]},{"providerOutcomeId":"0ML80190102_1","providerId":2,"providerOfferId":"1_80190102","label":"PIT Pirates","oddsAmerican":"\u002B120","oddsDecimal":2.2,"oddsDecimalDisplay":"2.20","oddsFractional":"6/5","participant":"PIT Pirates","participantType":"Team","main":true,"sortOrder":4271931,"tags":["SGP"],"participants":[{"id":"29924","name":"PIT Pirates","type":"Team"}]}],"offerSequence":0,"source":"5","displayGroupId":"7","main":true,"tags":["SGP","YourBetEligible","Cashout","FeaturedSubcategory","Default","PrimaryMarket"]}],[{"providerOfferId":"2_80190103","eventId":"32385266","eventGroupId":"84240","label":"Run Line","isSuspended":false,"isOpen":true,"offerSubcategoryId":4519,"isSubcategoryFeatured":true,"betOfferTypeId":1,"providerCriterionId":"2_0","outcomes":[{"providerOutcomeId":"0HC80190103N150_3","providerId":2,"providerOfferId":"2_80190103","label":"TEX Rangers","oddsAmerican":"\u002B130","oddsDecimal":2.3,"oddsDecimalDisplay":"2.30","oddsFractional":"13/10","line":-1.5,"participant":"TEX Rangers","participantType":"Team","main":true,"sortOrder":-1501,"tags":["MainPointLine","SGP"],"participants":[{"id":"29891","name":"TEX Rangers","type":"Team"}]},{"providerOutcomeId":"0HC80190103P150_1","providerId":2,"providerOfferId":"2_80190103","label":"WAS Nationals","oddsAmerican":"-155","oddsDecimal":1.6451613,"oddsDecimalDisplay":"1.64","oddsFractional":"20/31","line":1.5,"participant":"WAS Nationals","participantType":"Team","main":true,"sortOrder":-1499,"tags":["MainPointLine","SGP"],"participants":[{"id":"29836","name":"WAS Nationals","type":"Team"}]}],"offerSequence":0,"source":"5","displayGroupId":"7","main":true,"tags":["SGP","YourBetEligible","Cashout","FeaturedSubcategory","Default","PrimaryMarket"]},{"providerOfferId":"3_80190103","eventId":"32385266","eventGroupId":"84240","label":"Total","isSuspended":false,"isOpen":true,"offerSubcategoryId":4519,"isSubcategoryFeatured":true,"betOfferTypeId":6,"providerCriterionId":"3_0","outcomes":[{"providerOutcomeId":"0OU80190103O950_1","providerId":2,"providerOfferId":"3_80190103","label":"Over","oddsAmerican":"-105","oddsDecimal":1.95238096,"oddsDecimalDisplay":"1.95","oddsFractional":"20/21","line":9.5,"participant":"","participantType":"Unknown","main":true,"sortOrder":9500,"tags":["ProgressiveParlayTeamEligible","MainPointLine","SGP"]},{"providerOutcomeId":"0OU80190103U950_3","providerId":2,"providerOfferId":"3_80190103","label":"Under","oddsAmerican":"-115","oddsDecimal":1.86956522,"oddsDecimalDisplay":"1.86","oddsFractional":"20/23","line":9.5,"participant":"","participantType":"Unknown","main":true,"sortOrder":9502,"tags":["ProgressiveParlayTeamEligible","MainPointLine","SGP"]}],"offerSequence":0,"source":"5","displayGroupId":"7","main":true,"tags":["ProgressiveParlayTeamEligible","SGP","YourBetEligible","Cashout","FeaturedSubcategory","Default","PrimaryMarket"]},{"providerOfferId":"1_80190103","eventId":"32385266","eventGroupId":"84240","label":"Moneyline","isSuspended":false,"isOpen":true,"offerSubcategoryId":4519,"isSubcategoryFeatured":true,"betOfferTypeId":2,"providerCriterionId":"1_0","outcomes":[{"providerOutcomeId":"0ML80190103_3","providerId":2,"providerOfferId":"1_80190103","label":"TEX Rangers","oddsAmerican":"-125","oddsDecimal":1.8,"oddsDecimalDisplay":"1.80","oddsFractional":"4/5","participant":"TEX Rangers","participantType":"Team","main":true,"sortOrder":4251942,"tags":["SGP"],"participants":[{"id":"29891","name":"TEX Rangers","type":"Team"}]},{"providerOutcomeId":"0ML80190103_1","providerId":2,"providerOfferId":"1_80190103","label":"WAS Nationals","oddsAmerican":"\u002B105","oddsDecimal":2.05,"oddsDecimalDisplay":"2.05","oddsFractional":"21/20","participant":"WAS Nationals","participantType":"Team","main":true,"sortOrder":4271938,"tags":["SGP"],"participants":[{"id":"29836","name":"WAS Nationals","type":"Team"}]}],"offerSequence":0,"source":"5","displayGroupId":"7","main":true,"tags":["SGP","YourBetEligible","Cashout","FeaturedSubcategory","Default","PrimaryMarket"]}],[{"providerOfferId":"2_80190108","eventId":"32385268","eventGroupId":"84240","label":"Run Line","isSuspended":false,"isOpen":true,"offerSubcategoryId":4519,"isSubcategoryFeatured":true,"betOfferTypeId":1,"providerCriterionId":"2_0","outcomes":[{"providerOutcomeId":"0HC80190108P150_3","providerId":2,"providerOfferId":"2_80190108","label":"BOS Red Sox","oddsAmerican":"-142","oddsDecimal":1.70422536,"oddsDecimalDisplay":"1.70","oddsFractional":"50/71","line":1.5,"participant":"BOS Red Sox","participantType":"Team","main":true,"sortOrder":1499,"tags":["MainPointLine","SGP"],"participants":[{"id":"29976","name":"BOS Red Sox","type":"Team"}]},{"providerOutcomeId":"0HC80190108N150_1","providerId":2,"providerOfferId":"2_80190108","label":"NY Yankees","oddsAmerican":"\u002B120","oddsDecimal":2.2,"oddsDecimalDisplay":"2.20","oddsFractional":"6/5","line":-1.5,"participant":"NY Yankees","participantType":"Team","main":true,"sortOrder":1501,"tags":["MainPointLine","SGP"],"participants":[{"id":"29825","name":"NY Yankees","type":"Team"}]}],"offerSequence":0,"source":"5","displayGroupId":"7","main":true,"tags":["SGP","YourBetEligible","Cashout","FeaturedSubcategory","Default","PrimaryMarket"]},{"providerOfferId":"3_80190108","eventId":"32385268","eventGroupId":"84240","label":"Total","isSuspended":false,"isOpen":true,"offerSubcategoryId":4519,"isSubcategoryFeatured":true,"betOfferTypeId":6,"providerCriterionId":"3_0","outcomes":[{"providerOutcomeId":"0OU80190108O900_1","providerId":2,"providerOfferId":"3_80190108","label":"Over","oddsAmerican":"-118","oddsDecimal":1.84745763,"oddsDecimalDisplay":"1.84","oddsFractional":"50/59","line":9,"participant":"","participantType":"Unknown","main":true,"sortOrder":9000,"tags":["ProgressiveParlayTeamEligible","MainPointLine","SGP"]},{"providerOutcomeId":"0OU80190108U900_3","providerId":2,"providerOfferId":"3_80190108","label":"Under","oddsAmerican":"-102","oddsDecimal":1.98039216,"oddsDecimalDisplay":"1.98","oddsFractional":"50/51","line":9,"participant":"","participantType":"Unknown","main":true,"sortOrder":9002,"tags":["ProgressiveParlayTeamEligible","MainPointLine","SGP"]}],"offerSequence":0,"source":"5","displayGroupId":"7","main":true,"tags":["ProgressiveParlayTeamEligible","SGP","YourBetEligible","Cashout","FeaturedSubcategory","Default","PrimaryMarket"]},{"providerOfferId":"1_80190108","eventId":"32385268","eventGroupId":"84240","label":"Moneyline","isSuspended":false,"isOpen":true,"offerSubcategoryId":4519,"isSubcategoryFeatured":true,"betOfferTypeId":2,"providerCriterionId":"1_0","outcomes":[{"providerOutcomeId":"0ML80190108_3","providerId":2,"providerOfferId":"1_80190108","label":"BOS Red Sox","oddsAmerican":"\u002B150","oddsDecimal":2.5,"oddsDecimalDisplay":"2.50","oddsFractional":"6/4","participant":"BOS Red Sox","participantType":"Team","main":true,"sortOrder":4251977,"tags":["SGP"],"participants":[{"id":"29976","name":"BOS Red Sox","type":"Team"}]},{"providerOutcomeId":"0ML80190108_1","providerId":2,"providerOfferId":"1_80190108","label":"NY Yankees","oddsAmerican":"-180","oddsDecimal":1.55555556,"oddsDecimalDisplay":"1.55","oddsFractional":"5/9","participant":"NY Yankees","participantType":"Team","main":true,"sortOrder":4271973,"tags":["SGP"],"participants":[{"id":"29825","name":"NY Yankees","type":"Team"}]}],"offerSequence":0,"source":"5","displayGroupId":"7","main":true,"tags":["SGP","YourBetEligible","Cashout","FeaturedSubcategory","Default","PrimaryMarket"]}],[{"providerOfferId":"2_80190115","eventId":"32385271","eventGroupId":"84240","label":"Run Line","isSuspended":false,"isOpen":true,"offerSubcategoryId":4519,"isSubcategoryFeatured":true,"betOfferTypeId":1,"providerCriterionId":"2_0","outcomes":[{"providerOutcomeId":"0HC80190115N150_3","providerId":2,"providerOfferId":"2_80190115","label":"ARI Diamondbacks","oddsAmerican":"\u002B150","oddsDecimal":2.5,"oddsDecimalDisplay":"2.50","oddsFractional":"6/4","line":-1.5,"participant":"ARI Diamondbacks","participantType":"Team","main":true,"sortOrder":-1501,"tags":["MainPointLine","SGP"],"participants":[{"id":"29934","name":"ARI Diamondbacks","type":"Team"}]},{"providerOutcomeId":"0HC80190115P150_1","providerId":2,"providerOfferId":"2_80190115","label":"CIN Reds","oddsAmerican":"-180","oddsDecimal":1.55555556,"oddsDecimalDisplay":"1.55","oddsFractional":"5/9","line":1.5,"participant":"CIN Reds","participantType":"Team","main":true,"sortOrder":-1499,"tags":["MainPointLine","SGP"],"participants":[{"id":"29919","name":"CIN Reds","type":"Team"}]}],"offerSequence":0,"source":"5","displayGroupId":"7","main":true,"tags":["SGP","YourBetEligible","Cashout","FeaturedSubcategory","Default","PrimaryMarket"]},{"providerOfferId":"3_80190115","eventId":"32385271","eventGroupId":"84240","label":"Total","isSuspended":false,"isOpen":true,"offerSubcategoryId":4519,"isSubcategoryFeatured":true,"betOfferTypeId":6,"providerCriterionId":"3_0","outcomes":[{"providerOutcomeId":"0OU80190115O950_1","providerId":2,"providerOfferId":"3_80190115","label":"Over","oddsAmerican":"-102","oddsDecimal":1.98039216,"oddsDecimalDisplay":"1.98","oddsFractional":"50/51","line":9.5,"participant":"","participantType":"Unknown","main":true,"sortOrder":9500,"tags":["ProgressiveParlayTeamEligible","MainPointLine","SGP"]},{"providerOutcomeId":"0OU80190115U950_3","providerId":2,"providerOfferId":"3_80190115","label":"Under","oddsAmerican":"-118","oddsDecimal":1.84745763,"oddsDecimalDisplay":"1.84","oddsFractional":"50/59","line":9.5,"participant":"","participantType":"Unknown","main":true,"sortOrder":9502,"tags":["ProgressiveParlayTeamEligible","MainPointLine","SGP"]}],"offerSequence":0,"source":"5","displayGroupId":"7","main":true,"tags":["ProgressiveParlayTeamEligible","SGP","YourBetEligible","Cashout","FeaturedSubcategory","Default","PrimaryMarket"]},{"providerOfferId":"1_80190115","eventId":"32385271","eventGroupId":"84240","label":"Moneyline","isSuspended":false,"isOpen":true,"offerSubcategoryId":4519,"isSubcategoryFeatured":true,"betOfferTypeId":2,"providerCriterionId":"1_0","outcomes":[{"providerOutcomeId":"0ML80190115_3","providerId":2,"providerOfferId":"1_80190115","label":"ARI Diamondbacks","oddsAmerican":"-112","oddsDecimal":1.89285715,"oddsDecimalDisplay":"1.89","oddsFractional":"25/28","participant":"ARI Diamondbacks","participantType":"Team","main":true,"sortOrder":4252026,"tags":["SGP"],"participants":[{"id":"29934","name":"ARI Diamondbacks","type":"Team"}]},{"providerOutcomeId":"0ML80190115_1","providerId":2,"providerOfferId":"1_80190115","label":"CIN Reds","oddsAmerican":"-108","oddsDecimal":1.92592593,"oddsDecimalDisplay":"1.92","oddsFractional":"25/27","participant":"CIN Reds","participantType":"Team","main":true,"sortOrder":4272022,"tags":["SGP"],"participants":[{"id":"29919","name":"CIN Reds","type":"Team"}]}],"offerSequence":0,"source":"5","displayGroupId":"7","main":true,"tags":["SGP","YourBetEligible","Cashout","FeaturedSubcategory","Default","PrimaryMarket"]}],[{"providerOfferId":"2_80190128","eventId":"32385277","eventGroupId":"84240","label":"Run Line","isSuspended":false,"isOpen":true,"offerSubcategoryId":4519,"isSubcategoryFeatured":true,"betOfferTypeId":1,"providerCriterionId":"2_0","outcomes":[{"providerOutcomeId":"0HC80190128N150_3","providerId":2,"providerOfferId":"2_80190128","label":"HOU Astros","oddsAmerican":"\u002B154","oddsDecimal":2.54,"oddsDecimalDisplay":"2.54","oddsFractional":"77/50","line":-1.5,"participant":"HOU Astros","participantType":"Team","main":true,"sortOrder":-1501,"tags":["MainPointLine","SGP"],"participants":[{"id":"29882","name":"HOU Astros","type":"Team"}]},{"providerOutcomeId":"0HC80190128P150_1","providerId":2,"providerOfferId":"2_80190128","label":"CLE Guardians","oddsAmerican":"-185","oddsDecimal":1.54054055,"oddsDecimalDisplay":"1.54","oddsFractional":"20/37","line":1.5,"participant":"CLE Guardians","participantType":"Team","main":true,"sortOrder":-1499,"tags":["MainPointLine","SGP"],"participants":[{"id":"29913","name":"CLE Guardians","type":"Team"}]}],"offerSequence":0,"source":"5","displayGroupId":"7","main":true,"tags":["SGP","YourBetEligible","Cashout","FeaturedSubcategory","Default","PrimaryMarket"]},{"providerOfferId":"3_80190128","eventId":"32385277","eventGroupId":"84240","label":"Total","isSuspended":false,"isOpen":true,"offerSubcategoryId":4519,"isSubcategoryFeatured":true,"betOfferTypeId":6,"providerCriterionId":"3_0","outcomes":[{"providerOutcomeId":"0OU80190128O850_1","providerId":2,"providerOfferId":"3_80190128","label":"Over","oddsAmerican":"-105","oddsDecimal":1.95238096,"oddsDecimalDisplay":"1.95","oddsFractional":"20/21","line":8.5,"participant":"","participantType":"Unknown","main":true,"sortOrder":8500,"tags":["ProgressiveParlayTeamEligible","MainPointLine","SGP"]},{"providerOutcomeId":"0OU80190128U850_3","providerId":2,"providerOfferId":"3_80190128","label":"Under","oddsAmerican":"-115","oddsDecimal":1.86956522,"oddsDecimalDisplay":"1.86","oddsFractional":"20/23","line":8.5,"participant":"","participantType":"Unknown","main":true,"sortOrder":8502,"tags":["ProgressiveParlayTeamEligible","MainPointLine","SGP"]}],"offerSequence":0,"source":"5","displayGroupId":"7","main":true,"tags":["ProgressiveParlayTeamEligible","SGP","YourBetEligible","Cashout","FeaturedSubcategory","Default","PrimaryMarket"]},{"providerOfferId":"1_80190128","eventId":"32385277","eventGroupId":"84240","label":"Moneyline","isSuspended":false,"isOpen":true,"offerSubcategoryId":4519,"isSubcategoryFeatured":true,"betOfferTypeId":2,"providerCriterionId":"1_0","outcomes":[{"providerOutcomeId":"0ML80190128_3","providerId":2,"providerOfferId":"1_80190128","label":"HOU Astros","oddsAmerican":"-108","oddsDecimal":1.92592593,"oddsDecimalDisplay":"1.92","oddsFractional":"25/27","participant":"HOU Astros","participantType":"Team","main":true,"sortOrder":4252117,"tags":["SGP"],"participants":[{"id":"29882","name":"HOU Astros","type":"Team"}]},{"providerOutcomeId":"0ML80190128_1","providerId":2,"providerOfferId":"1_80190128","label":"CLE Guardians","oddsAmerican":"-112","oddsDecimal":1.89285715,"oddsDecimalDisplay":"1.89","oddsFractional":"25/28","participant":"CLE Guardians","participantType":"Team","main":true,"sortOrder":4272113,"tags":["SGP"],"participants":[{"id":"29913","name":"CLE Guardians","type":"Team"}]}],"offerSequence":0,"source":"5","displayGroupId":"7","main":true,"tags":["SGP","YourBetEligible","Cashout","FeaturedSubcategory","Default","PrimaryMarket"]}],[{"providerOfferId":"2_80190136","eventId":"32385281","eventGroupId":"84240","label":"Run Line","isSuspended":false,"isOpen":true,"offerSubcategoryId":4519,"isSubcategoryFeatured":true,"betOfferTypeId":1,"providerCriterionId":"2_0","outcomes":[{"providerOutcomeId":"0HC80190136N150_3","providerId":2,"providerOfferId":"2_80190136","label":"KC Royals","oddsAmerican":"-102","oddsDecimal":1.98039216,"oddsDecimalDisplay":"1.98","oddsFractional":"50/51","line":-1.5,"participant":"KC Royals","participantType":"Team","main":true,"sortOrder":-1501,"tags":["MainPointLine","SGP"],"participants":[{"id":"29965","name":"KC Royals","type":"Team"}]},{"providerOutcomeId":"0HC80190136P150_1","providerId":2,"providerOfferId":"2_80190136","label":"CHI White Sox","oddsAmerican":"-118","oddsDecimal":1.84745763,"oddsDecimalDisplay":"1.84","oddsFractional":"50/59","line":1.5,"participant":"CHI White Sox","participantType":"Team","main":true,"sortOrder":-1499,"tags":["MainPointLine","SGP"],"participants":[{"id":"29970","name":"CHI White Sox","type":"Team"}]}],"offerSequence":0,"source":"5","displayGroupId":"7","main":true,"tags":["SGP","YourBetEligible","Cashout","FeaturedSubcategory","Default","PrimaryMarket"]},{"providerOfferId":"3_80190136","eventId":"32385281","eventGroupId":"84240","label":"Total","isSuspended":false,"isOpen":true,"offerSubcategoryId":4519,"isSubcategoryFeatured":true,"betOfferTypeId":6,"providerCriterionId":"3_0","outcomes":[{"providerOutcomeId":"0OU80190136O800_1","providerId":2,"providerOfferId":"3_80190136","label":"Over","oddsAmerican":"-115","oddsDecimal":1.86956522,"oddsDecimalDisplay":"1.86","oddsFractional":"20/23","line":8,"participant":"","participantType":"Unknown","main":true,"sortOrder":8000,"tags":["ProgressiveParlayTeamEligible","MainPointLine","SGP"]},{"providerOutcomeId":"0OU80190136U800_3","providerId":2,"providerOfferId":"3_80190136","label":"Under","oddsAmerican":"-105","oddsDecimal":1.95238096,"oddsDecimalDisplay":"1.95","oddsFractional":"20/21","line":8,"participant":"","participantType":"Unknown","main":true,"sortOrder":8002,"tags":["ProgressiveParlayTeamEligible","MainPointLine","SGP"]}],"offerSequence":0,"source":"5","displayGroupId":"7","main":true,"tags":["ProgressiveParlayTeamEligible","SGP","YourBetEligible","Cashout","FeaturedSubcategory","Default","PrimaryMarket"]},{"providerOfferId":"1_80190136","eventId":"32385281","eventGroupId":"84240","label":"Moneyline","isSuspended":false,"isOpen":true,"offerSubcategoryId":4519,"isSubcategoryFeatured":true,"betOfferTypeId":2,"providerCriterionId":"1_0","outcomes":[{"providerOutcomeId":"0ML80190136_3","providerId":2,"providerOfferId":"1_80190136","label":"KC Royals","oddsAmerican":"-175","oddsDecimal":1.57142858,"oddsDecimalDisplay":"1.57","oddsFractional":"4/7","participant":"KC Royals","participantType":"Team","main":true,"sortOrder":4252173,"tags":["SGP"],"participants":[{"id":"29965","name":"KC Royals","type":"Team"}]},{"providerOutcomeId":"0ML80190136_1","providerId":2,"providerOfferId":"1_80190136","label":"CHI White Sox","oddsAmerican":"\u002B145","oddsDecimal":2.45,"oddsDecimalDisplay":"2.45","oddsFractional":"29/20","participant":"CHI White Sox","participantType":"Team","main":true,"sortOrder":4272169,"tags":["SGP"],"participants":[{"id":"29970","name":"CHI White Sox","type":"Team"}]}],"offerSequence":0,"source":"5","displayGroupId":"7","main":true,"tags":["SGP","YourBetEligible","Cashout","FeaturedSubcategory","Default","PrimaryMarket"]}],[{"providerOfferId":"2_80190150","eventId":"32385286","eventGroupId":"84240","label":"Run Line","isSuspended":false,"isOpen":true,"offerSubcategoryId":4519,"isSubcategoryFeatured":true,"betOfferTypeId":1,"providerCriterionId":"2_0","outcomes":[{"providerOutcomeId":"0HC80190150P150_3","providerId":2,"providerOfferId":"2_80190150","label":"SD Padres","oddsAmerican":"-162","oddsDecimal":1.61728396,"oddsDecimalDisplay":"1.61","oddsFractional":"50/81","line":1.5,"participant":"SD Padres","participantType":"Team","main":true,"sortOrder":1499,"tags":["MainPointLine","SGP"],"participants":[{"id":"29942","name":"SD Padres","type":"Team"}]},{"providerOutcomeId":"0HC80190150N150_1","providerId":2,"providerOfferId":"2_80190150","label":"MIL Brewers","oddsAmerican":"\u002B136","oddsDecimal":2.36,"oddsDecimalDisplay":"2.36","oddsFractional":"34/25","line":-1.5,"participant":"MIL Brewers","participantType":"Team","main":true,"sortOrder":1501,"tags":["MainPointLine","SGP"],"participants":[{"id":"29847","name":"MIL Brewers","type":"Team"}]}],"offerSequence":0,"source":"5","displayGroupId":"7","main":true,"tags":["SGP","YourBetEligible","Cashout","FeaturedSubcategory","Default","PrimaryMarket"]},{"providerOfferId":"3_80190150","eventId":"32385286","eventGroupId":"84240","label":"Total","isSuspended":false,"isOpen":true,"offerSubcategoryId":4519,"isSubcategoryFeatured":true,"betOfferTypeId":6,"providerCriterionId":"3_0","outcomes":[{"providerOutcomeId":"0OU80190150O850_1","providerId":2,"providerOfferId":"3_80190150","label":"Over","oddsAmerican":"-118","oddsDecimal":1.84745763,"oddsDecimalDisplay":"1.84","oddsFractional":"50/59","line":8.5,"participant":"","participantType":"Unknown","main":true,"sortOrder":8500,"tags":["ProgressiveParlayTeamEligible","MainPointLine","SGP"]},{"providerOutcomeId":"0OU80190150U850_3","providerId":2,"providerOfferId":"3_80190150","label":"Under","oddsAmerican":"-102","oddsDecimal":1.98039216,"oddsDecimalDisplay":"1.98","oddsFractional":"50/51","line":8.5,"participant":"","participantType":"Unknown","main":true,"sortOrder":8502,"tags":["ProgressiveParlayTeamEligible","MainPointLine","SGP"]}],"offerSequence":0,"source":"5","displayGroupId":"7","main":true,"tags":["ProgressiveParlayTeamEligible","SGP","YourBetEligible","Cashout","FeaturedSubcategory","Default","PrimaryMarket"]},{"providerOfferId":"1_80190150","eventId":"32385286","eventGroupId":"84240","label":"Moneyline","isSuspended":false,"isOpen":true,"offerSubcategoryId":4519,"isSubcategoryFeatured":true,"betOfferTypeId":2,"providerCriterionId":"1_0","outcomes":[{"providerOutcomeId":"0ML80190150_3","providerId":2,"providerOfferId":"1_80190150","label":"SD Padres","oddsAmerican":"\u002B124","oddsDecimal":2.24,"oddsDecimalDisplay":"2.24","oddsFractional":"31/25","participant":"SD Padres","participantType":"Team","main":true,"sortOrder":4252271,"tags":["SGP"],"participants":[{"id":"29942","name":"SD Padres","type":"Team"}]},{"providerOutcomeId":"0ML80190150_1","providerId":2,"providerOfferId":"1_80190150","label":"MIL Brewers","oddsAmerican":"-148","oddsDecimal":1.67567568,"oddsDecimalDisplay":"1.67","oddsFractional":"25/37","participant":"MIL Brewers","participantType":"Team","main":true,"sortOrder":4272267,"tags":["SGP"],"participants":[{"id":"29847","name":"MIL Brewers","type":"Team"}]}],"offerSequence":0,"source":"5","displayGroupId":"7","main":true,"tags":["SGP","YourBetEligible","Cashout","FeaturedSubcategory","Default","PrimaryMarket"]}],[{"providerOfferId":"2_80190164","eventId":"32385293","eventGroupId":"84240","label":"Run Line","isSuspended":false,"isOpen":true,"offerSubcategoryId":4519,"isSubcategoryFeatured":true,"betOfferTypeId":1,"providerCriterionId":"2_0","outcomes":[{"providerOutcomeId":"0HC80190164N150_3","providerId":2,"providerOfferId":"2_80190164","label":"LA Dodgers","oddsAmerican":"\u002B136","oddsDecimal":2.36,"oddsDecimalDisplay":"2.36","oddsFractional":"34/25","line":-1.5,"participant":"LA Dodgers","participantType":"Team","main":true,"sortOrder":-1501,"tags":["MainPointLine","SGP"],"participants":[{"id":"29931","name":"LA Dodgers","type":"Team"}]},{"providerOutcomeId":"0HC80190164P150_1","providerId":2,"providerOfferId":"2_80190164","label":"STL Cardinals","oddsAmerican":"-162","oddsDecimal":1.61728396,"oddsDecimalDisplay":"1.61","oddsFractional":"50/81","line":1.5,"participant":"STL Cardinals","participantType":"Team","main":true,"sortOrder":-1499,"tags":["MainPointLine","SGP"],"participants":[{"id":"29851","name":"STL Cardinals","type":"Team"}]}],"offerSequence":0,"source":"5","displayGroupId":"7","main":true,"tags":["SGP","YourBetEligible","Cashout","FeaturedSubcategory","Default","PrimaryMarket"]},{"providerOfferId":"3_80190164","eventId":"32385293","eventGroupId":"84240","label":"Total","isSuspended":false,"isOpen":true,"offerSubcategoryId":4519,"isSubcategoryFeatured":true,"betOfferTypeId":6,"providerCriterionId":"3_0","outcomes":[{"providerOutcomeId":"0OU80190164O850_1","providerId":2,"providerOfferId":"3_80190164","label":"Over","oddsAmerican":"-122","oddsDecimal":1.81967214,"oddsDecimalDisplay":"1.81","oddsFractional":"50/61","line":8.5,"participant":"","participantType":"Unknown","main":true,"sortOrder":8500,"tags":["ProgressiveParlayTeamEligible","MainPointLine","SGP"]},{"providerOutcomeId":"0OU80190164U850_3","providerId":2,"providerOfferId":"3_80190164","label":"Under","oddsAmerican":"-102","oddsDecimal":1.98039216,"oddsDecimalDisplay":"1.98","oddsFractional":"50/51","line":8.5,"participant":"","participantType":"Unknown","main":true,"sortOrder":8502,"tags":["ProgressiveParlayTeamEligible","MainPointLine","SGP"]}],"offerSequence":0,"source":"5","displayGroupId":"7","main":true,"tags":["ProgressiveParlayTeamEligible","SGP","YourBetEligible","Cashout","FeaturedSubcategory","Default","PrimaryMarket"]},{"providerOfferId":"1_80190164","eventId":"32385293","eventGroupId":"84240","label":"Moneyline","isSuspended":false,"isOpen":true,"offerSubcategoryId":4519,"isSubcategoryFeatured":true,"betOfferTypeId":2,"providerCriterionId":"1_0","outcomes":[{"providerOutcomeId":"0ML80190164_3","providerId":2,"providerOfferId":"1_80190164","label":"LA Dodgers","oddsAmerican":"-130","oddsDecimal":1.76923077,"oddsDecimalDisplay":"1.76","oddsFractional":"10/13","participant":"LA Dodgers","participantType":"Team","main":true,"sortOrder":4252369,"tags":["SGP"],"participants":[{"id":"29931","name":"LA Dodgers","type":"Team"}]},{"providerOutcomeId":"0ML80190164_1","providerId":2,"providerOfferId":"1_80190164","label":"STL Cardinals","oddsAmerican":"\u002B110","oddsDecimal":2.1,"oddsDecimalDisplay":"2.10","oddsFractional":"11/10","participant":"STL Cardinals","participantType":"Team","main":true,"sortOrder":4272365,"tags":["SGP"],"participants":[{"id":"29851","name":"STL Cardinals","type":"Team"}]}],"offerSequence":0,"source":"5","displayGroupId":"7","main":true,"tags":["SGP","YourBetEligible","Cashout","FeaturedSubcategory","Default","PrimaryMarket"]}],[{"providerOfferId":"2_80190182","eventId":"32385297","eventGroupId":"84240","label":"Run Line","isSuspended":false,"isOpen":true,"offerSubcategoryId":4519,"isSubcategoryFeatured":true,"betOfferTypeId":1,"providerCriterionId":"2_0","outcomes":[{"providerOutcomeId":"0HC80190182N150_3","providerId":2,"providerOfferId":"2_80190182","label":"NY Mets","oddsAmerican":"-218","oddsDecimal":1.4587156,"oddsDecimalDisplay":"1.45","oddsFractional":"50/109","line":-1.5,"participant":"NY Mets","participantType":"Team","main":true,"sortOrder":-1501,"tags":["MainPointLine","SGP"],"participants":[{"id":"29840","name":"NY Mets","type":"Team"}]},{"providerOutcomeId":"0HC80190182P150_1","providerId":2,"providerOfferId":"2_80190182","label":"COL Rockies","oddsAmerican":"\u002B180","oddsDecimal":2.8,"oddsDecimalDisplay":"2.80","oddsFractional":"9/5","line":1.5,"participant":"COL Rockies","participantType":"Team","main":true,"sortOrder":-1499,"tags":["MainPointLine","SGP"],"participants":[{"id":"29957","name":"COL Rockies","type":"Team"}]}],"offerSequence":0,"source":"5","displayGroupId":"7","main":true,"tags":["SGP","YourBetEligible","Cashout","FeaturedSubcategory","Default","PrimaryMarket"]},{"providerOfferId":"3_80190182","eventId":"32385297","eventGroupId":"84240","label":"Total","isSuspended":false,"isOpen":true,"offerSubcategoryId":4519,"isSubcategoryFeatured":true,"betOfferTypeId":6,"providerCriterionId":"3_0","outcomes":[{"providerOutcomeId":"0OU80190182O1050_1","providerId":2,"providerOfferId":"3_80190182","label":"Over","oddsAmerican":"-115","oddsDecimal":1.86956522,"oddsDecimalDisplay":"1.86","oddsFractional":"20/23","line":10.5,"participant":"","participantType":"Unknown","main":true,"sortOrder":10500,"tags":["ProgressiveParlayTeamEligible","MainPointLine","SGP"]},{"providerOutcomeId":"0OU80190182U1050_3","providerId":2,"providerOfferId":"3_80190182","label":"Under","oddsAmerican":"-105","oddsDecimal":1.95238096,"oddsDecimalDisplay":"1.95","oddsFractional":"20/21","line":10.5,"participant":"","participantType":"Unknown","main":true,"sortOrder":10502,"tags":["ProgressiveParlayTeamEligible","MainPointLine","SGP"]}],"offerSequence":0,"source":"5","displayGroupId":"7","main":true,"tags":["ProgressiveParlayTeamEligible","SGP","YourBetEligible","Cashout","FeaturedSubcategory","Default","PrimaryMarket"]},{"providerOfferId":"1_80190182","eventId":"32385297","eventGroupId":"84240","label":"Moneyline","isSuspended":false,"isOpen":true,"offerSubcategoryId":4519,"isSubcategoryFeatured":true,"betOfferTypeId":2,"providerCriterionId":"1_0","outcomes":[{"providerOutcomeId":"0ML80190182_3","providerId":2,"providerOfferId":"1_80190182","label":"NY Mets","oddsAmerican":"-325","oddsDecimal":1.30769231,"oddsDecimalDisplay":"1.30","oddsFractional":"4/13","participant":"NY Mets","participantType":"Team","main":true,"sortOrder":4252495,"tags":["SGP"],"participants":[{"id":"29840","name":"NY Mets","type":"Team"}]},{"providerOutcomeId":"0ML80190182_1","providerId":2,"providerOfferId":"1_80190182","label":"COL Rockies","oddsAmerican":"\u002B260","oddsDecimal":3.6,"oddsDecimalDisplay":"3.60","oddsFractional":"13/5","participant":"COL Rockies","participantType":"Team","main":true,"sortOrder":4272491,"tags":["SGP"],"participants":[{"id":"29957","name":"COL Rockies","type":"Team"}]}],"offerSequence":0,"source":"5","displayGroupId":"7","main":true,"tags":["SGP","YourBetEligible","Cashout","FeaturedSubcategory","Default","PrimaryMarket"]}],[{"providerOfferId":"2_80190248","eventId":"32385322","eventGroupId":"84240","label":"Run Line","isSuspended":false,"isOpen":true,"offerSubcategoryId":4519,"isSubcategoryFeatured":true,"betOfferTypeId":1,"providerCriterionId":"2_0","outcomes":[{"providerOutcomeId":"0HC80190248N150_3","providerId":2,"providerOfferId":"2_80190248","label":"SEA Mariners","oddsAmerican":"\u002B105","oddsDecimal":2.05,"oddsDecimalDisplay":"2.05","oddsFractional":"21/20","line":-1.5,"participant":"SEA Mariners","participantType":"Team","main":true,"sortOrder":-1501,"tags":["MainPointLine","SGP"],"participants":[{"id":"29815","name":"SEA Mariners","type":"Team"}]},{"providerOutcomeId":"0HC80190248P150_1","providerId":2,"providerOfferId":"2_80190248","label":"LA Angels","oddsAmerican":"-125","oddsDecimal":1.8,"oddsDecimalDisplay":"1.80","oddsFractional":"4/5","line":1.5,"participant":"LA Angels","participantType":"Team","main":true,"sortOrder":-1499,"tags":["MainPointLine","SGP"],"participants":[{"id":"29901","name":"LA Angels","type":"Team"}]}],"offerSequence":0,"source":"5","displayGroupId":"7","main":true,"tags":["SGP","YourBetEligible","Cashout","FeaturedSubcategory","Default","PrimaryMarket"]},{"providerOfferId":"3_80190248","eventId":"32385322","eventGroupId":"84240","label":"Total","isSuspended":false,"isOpen":true,"offerSubcategoryId":4519,"isSubcategoryFeatured":true,"betOfferTypeId":6,"providerCriterionId":"3_0","outcomes":[{"providerOutcomeId":"0OU80190248O950_1","providerId":2,"providerOfferId":"3_80190248","label":"Over","oddsAmerican":"-102","oddsDecimal":1.98039216,"oddsDecimalDisplay":"1.98","oddsFractional":"50/51","line":9.5,"participant":"","participantType":"Unknown","main":true,"sortOrder":9500,"tags":["ProgressiveParlayTeamEligible","MainPointLine","SGP"]},{"providerOutcomeId":"0OU80190248U950_3","providerId":2,"providerOfferId":"3_80190248","label":"Under","oddsAmerican":"-118","oddsDecimal":1.84745763,"oddsDecimalDisplay":"1.84","oddsFractional":"50/59","line":9.5,"participant":"","participantType":"Unknown","main":true,"sortOrder":9502,"tags":["ProgressiveParlayTeamEligible","MainPointLine","SGP"]}],"offerSequence":0,"source":"5","displayGroupId":"7","main":true,"tags":["ProgressiveParlayTeamEligible","SGP","YourBetEligible","Cashout","FeaturedSubcategory","Default","PrimaryMarket"]},{"providerOfferId":"1_80190248","eventId":"32385322","eventGroupId":"84240","label":"Moneyline","isSuspended":false,"isOpen":true,"offerSubcategoryId":4519,"isSubcategoryFeatured":true,"betOfferTypeId":2,"providerCriterionId":"1_0","outcomes":[{"providerOutcomeId":"0ML80190248_3","providerId":2,"providerOfferId":"1_80190248","label":"SEA Mariners","oddsAmerican":"-155","oddsDecimal":1.6451613,"oddsDecimalDisplay":"1.64","oddsFractional":"20/31","participant":"SEA Mariners","participantType":"Team","main":true,"sortOrder":4254616,"tags":["SGP"],"participants":[{"id":"29815","name":"SEA Mariners","type":"Team"}]},{"providerOutcomeId":"0ML80190248_1","providerId":2,"providerOfferId":"1_80190248","label":"LA Angels","oddsAmerican":"\u002B130","oddsDecimal":2.3,"oddsDecimalDisplay":"2.30","oddsFractional":"13/10","participant":"LA Angels","participantType":"Team","main":true,"sortOrder":4274612,"tags":["SGP"],"participants":[{"id":"29901","name":"LA Angels","type":"Team"}]}],"offerSequence":0,"source":"5","displayGroupId":"7","main":true,"tags":["SGP","YourBetEligible","Cashout","FeaturedSubcategory","Default","PrimaryMarket"]}],[{"providerOfferId":"2_80190250","eventId":"32385324","eventGroupId":"84240","label":"Run Line","isSuspended":false,"isOpen":true,"offerSubcategoryId":4519,"isSubcategoryFeatured":true,"betOfferTypeId":1,"providerCriterionId":"2_0","outcomes":[{"providerOutcomeId":"0HC80190250N150_3","providerId":2,"providerOfferId":"2_80190250","label":"ATL Braves","oddsAmerican":"\u002B130","oddsDecimal":2.3,"oddsDecimalDisplay":"2.30","oddsFractional":"13/10","line":-1.5,"participant":"ATL Braves","participantType":"Team","main":true,"sortOrder":-1501,"tags":["MainPointLine","SGP"],"participants":[{"id":"29861","name":"ATL Braves","type":"Team"}]},{"providerOutcomeId":"0HC80190250P150_1","providerId":2,"providerOfferId":"2_80190250","label":"SF Giants","oddsAmerican":"-155","oddsDecimal":1.6451613,"oddsDecimalDisplay":"1.64","oddsFractional":"20/31","line":1.5,"participant":"SF Giants","participantType":"Team","main":true,"sortOrder":-1499,"tags":["MainPointLine","SGP"],"participants":[{"id":"29945","name":"SF Giants","type":"Team"}]}],"offerSequence":0,"source":"5","displayGroupId":"7","main":true,"tags":["SGP","YourBetEligible","Cashout","FeaturedSubcategory","Default","PrimaryMarket"]},{"providerOfferId":"3_80190250","eventId":"32385324","eventGroupId":"84240","label":"Total","isSuspended":false,"isOpen":true,"offerSubcategoryId":4519,"isSubcategoryFeatured":true,"betOfferTypeId":6,"providerCriterionId":"3_0","outcomes":[{"providerOutcomeId":"0OU80190250O750_1","providerId":2,"providerOfferId":"3_80190250","label":"Over","oddsAmerican":"-108","oddsDecimal":1.92592593,"oddsDecimalDisplay":"1.92","oddsFractional":"25/27","line":7.5,"participant":"","participantType":"Unknown","main":true,"sortOrder":7500,"tags":["ProgressiveParlayTeamEligible","MainPointLine","SGP"]},{"providerOutcomeId":"0OU80190250U750_3","providerId":2,"providerOfferId":"3_80190250","label":"Under","oddsAmerican":"-112","oddsDecimal":1.89285715,"oddsDecimalDisplay":"1.89","oddsFractional":"25/28","line":7.5,"participant":"","participantType":"Unknown","main":true,"sortOrder":7502,"tags":["ProgressiveParlayTeamEligible","MainPointLine","SGP"]}],"offerSequence":0,"source":"5","displayGroupId":"7","main":true,"tags":["ProgressiveParlayTeamEligible","SGP","YourBetEligible","Cashout","FeaturedSubcategory","Default","PrimaryMarket"]},{"providerOfferId":"1_80190250","eventId":"32385324","eventGroupId":"84240","label":"Moneyline","isSuspended":false,"isOpen":true,"offerSubcategoryId":4519,"isSubcategoryFeatured":true,"betOfferTypeId":2,"providerCriterionId":"1_0","outcomes":[{"providerOutcomeId":"0ML80190250_3","providerId":2,"providerOfferId":"1_80190250","label":"ATL Braves","oddsAmerican":"-135","oddsDecimal":1.74074075,"oddsDecimalDisplay":"1.74","oddsFractional":"20/27","participant":"ATL Braves","participantType":"Team","main":true,"sortOrder":4254630,"tags":["SGP"],"participants":[{"id":"29861","name":"ATL Braves","type":"Team"}]},{"providerOutcomeId":"0ML80190250_1","providerId":2,"providerOfferId":"1_80190250","label":"SF Giants","oddsAmerican":"\u002B114","oddsDecimal":2.14,"oddsDecimalDisplay":"2.14","oddsFractional":"57/50","participant":"SF Giants","participantType":"Team","main":true,"sortOrder":4274626,"tags":["SGP"],"participants":[{"id":"29945","name":"SF Giants","type":"Team"}]}],"offerSequence":0,"source":"5","displayGroupId":"7","main":true,"tags":["SGP","YourBetEligible","Cashout","FeaturedSubcategory","Default","PrimaryMarket"]}]]},"tags":["SGP"]},{"subcategoryId":13168,"name":"Alternate Run Line","tags":["SGP"]},{"subcategoryId":13169,"name":"Alternate Total Runs","tags":["SGP"]},{"subcategoryId":6618,"name":"Listed Pitcher"},{"subcategoryId":6694,"name":"Total Runs (3-Way)"}],"tags":["SGP"]},{"offerCategoryId":743,"name":"Batter Props","tags":["SGP"]},{"offerCategoryId":1031,"name":"Pitcher Props","tags":["SGP"]},{"offerCategoryId":1196,"name":"Series Props"},{"offerCategoryId":1782,"name":"Either Player Props","tags":["SGP"]},{"offerCategoryId":1781,"name":"Combined Player Props","tags":["SGP"]},{"offerCategoryId":1024,"name":"1st Inning","tags":["SGP"]},{"offerCategoryId":988,"name":"Plate Appearance"},{"offerCategoryId":1650,"name":"1st of Game","tags":["SGP"]},{"offerCategoryId":1626,"name":"1st X Innings","tags":["SGP"]},{"offerCategoryId":729,"name":"Innings","tags":["SGP"]},{"offerCategoryId":1671,"name":"Game Totals"},{"offerCategoryId":1674,"name":"Team Totals","tags":["SGP"]},{"offerCategoryId":724,"name":"Game Props","tags":["SGP"]},{"offerCategoryId":1133,"name":"Correct Score"},{"offerCategoryId":1774,"name":"Champion"},{"offerCategoryId":1762,"name":"Leagues"},{"offerCategoryId":1764,"name":"Divisions"},{"offerCategoryId":1765,"name":"Playoffs/Seeds"},{"offerCategoryId":684,"name":"Awards"},{"offerCategoryId":1250,"name":"H2H Player Props"},{"offerCategoryId":1798,"name":"Player Specials"}],"events":[{"eventId":"32385261","displayGroupId":"7","eventGroupId":"84240","eventGroupName":"MLB","name":"MIA Marlins @ TB Rays","nameIdentifier":"MIA Marlins @ TB Rays","startDate":"2025-06-06T17:10:00.0000000Z","teamName1":"MIA Marlins","teamName2":"TB Rays","teamShortName1":"MIA","teamShortName2":"TB","team1":{"teamId":29953,"name":"MIA Marlins","shortName":"MIA"},"team2":{"teamId":29880,"name":"TB Rays","shortName":"TB"},"eventStatus":{"state":"NOT_STARTED","isClockDisabled":false,"minute":0,"second":0,"isClockRunning":false},"eventScorecard":{"scorecardComponentId":1},"mediaList":[{"mediaProviderName":"BetRadarStats","mediaId":"55310343","mediaTypeName":"Stats","metadata":{},"updatedAt":"2025-06-06T06:26:40.3252705Z"},{"mediaProviderName":"BetRadarV3","mediaId":"55310343","mediaTypeName":"MatchTracker","metadata":{"betRadarCoverage":"3"},"updatedAt":"2025-06-06T06:26:40.3252705Z"},{"mediaProviderName":"BetRadarV3","mediaId":"55310343","mediaTypeName":"Scoreboard","metadata":{"betRadarCoverage":"3"},"updatedAt":"2025-06-06T06:26:40.3252705Z"}],"liveBettingOffered":false,"liveBettingEnabled":false,"tags":["FeaturedSubcategory","Flashbet","MatchTracker","PrePack","ProgressiveParlayEligible","ProgressiveParlayTeamEligible","SGP","Scoreboard","SgpDynamicOdds","Stats","YourBetEligible"],"flashBetOfferCount":0,"eventAttributes":{"homeTeamStartingPitcherName":"Zack Littell"},"eventMetadata":{"participantMetadata":{"homeTeamStartingPitcherPlayerId":"109259","homeTeamStartingPitcherName":"Zack Littell"},"mediaMetadata":{"BetRadarStats_Stats":{},"BetRadarV3_MatchTracker":{},"BetRadarV3_Scoreboard":{}}}},{"eventId":"32385265","displayGroupId":"7","eventGroupId":"84240","eventGroupName":"MLB","name":"PHI Phillies @ PIT Pirates","nameIdentifier":"PHI Phillies @ PIT Pirates","startDate":"2025-06-06T22:40:00.0000000Z","teamName1":"PHI Phillies","teamName2":"PIT Pirates","teamShortName1":"PHI","teamShortName2":"PIT","team1":{"teamId":29857,"name":"PHI Phillies","shortName":"PHI"},"team2":{"teamId":29924,"name":"PIT Pirates","shortName":"PIT"},"eventStatus":{"state":"NOT_STARTED","isClockDisabled":false,"minute":0,"second":0,"isClockRunning":false},"eventScorecard":{"scorecardComponentId":1},"mediaList":[{"mediaProviderName":"BetRadarStats","mediaId":"55309717","mediaTypeName":"Stats","metadata":{},"updatedAt":"2025-06-06T06:30:01.2666495Z"},{"mediaProviderName":"BetRadarV3","mediaId":"55309717","mediaTypeName":"MatchTracker","metadata":{"betRadarCoverage":"3"},"updatedAt":"2025-06-06T06:30:01.2666495Z"},{"mediaProviderName":"BetRadarV3","mediaId":"55309717","mediaTypeName":"Scoreboard","metadata":{"betRadarCoverage":"3"},"updatedAt":"2025-06-06T06:30:01.2666495Z"}],"liveBettingOffered":false,"liveBettingEnabled":false,"tags":["FeaturedSubcategory","Flashbet","MatchTracker","PrePack","ProgressiveParlayEligible","ProgressiveParlayTeamEligible","SGP","Scoreboard","SgpDynamicOdds","Stats","YourBetEligible"],"flashBetOfferCount":0,"eventAttributes":{"homeTeamStartingPitcherName":"Bailey Falter","awayTeamStartingPitcherName":"Joe Ross"},"eventMetadata":{"participantMetadata":{"homeTeamStartingPitcherPlayerId":"120109","awayTeamStartingPitcherPlayerId":"109669","homeTeamStartingPitcherName":"Bailey Falter","awayTeamStartingPitcherName":"Joe Ross"},"mediaMetadata":{"BetRadarStats_Stats":{},"BetRadarV3_MatchTracker":{},"BetRadarV3_Scoreboard":{}}}},{"eventId":"32385266","displayGroupId":"7","eventGroupId":"84240","eventGroupName":"MLB","name":"TEX Rangers @ WAS Nationals","nameIdentifier":"TEX Rangers @ WAS Nationals","startDate":"2025-06-06T22:45:00.0000000Z","teamName1":"TEX Rangers","teamName2":"WAS Nationals","teamShortName1":"TEX","teamShortName2":"WAS","team1":{"teamId":29891,"name":"TEX Rangers","shortName":"TEX"},"team2":{"teamId":29836,"name":"WAS Nationals","shortName":"WAS"},"eventStatus":{"state":"NOT_STARTED","isClockDisabled":false,"minute":0,"second":0,"isClockRunning":false},"eventScorecard":{"scorecardComponentId":1},"mediaList":[{"mediaProviderName":"BetRadarStats","mediaId":"55310557","mediaTypeName":"Stats","metadata":{},"updatedAt":"2025-06-06T06:30:35.8563273Z"},{"mediaProviderName":"BetRadarV3","mediaId":"55310557","mediaTypeName":"MatchTracker","metadata":{"betRadarCoverage":"3"},"updatedAt":"2025-06-06T06:30:35.8563273Z"},{"mediaProviderName":"BetRadarV3","mediaId":"55310557","mediaTypeName":"Scoreboard","metadata":{"betRadarCoverage":"3"},"updatedAt":"2025-06-06T06:30:35.8563273Z"}],"liveBettingOffered":false,"liveBettingEnabled":false,"tags":["FeaturedSubcategory","Flashbet","MatchTracker","PrePack","ProgressiveParlayEligible","ProgressiveParlayTeamEligible","SGP","Scoreboard","SgpDynamicOdds","Stats","YourBetEligible"],"flashBetOfferCount":0,"eventAttributes":{"homeTeamStartingPitcherName":"Michael Soroka","awayTeamStartingPitcherName":"Patrick Corbin"},"eventMetadata":{"participantMetadata":{"homeTeamStartingPitcherPlayerId":"109119","awayTeamStartingPitcherPlayerId":"109656","homeTeamStartingPitcherName":"Michael Soroka","awayTeamStartingPitcherName":"Patrick Corbin"},"mediaMetadata":{"BetRadarStats_Stats":{},"BetRadarV3_MatchTracker":{},"BetRadarV3_Scoreboard":{}}}},{"eventId":"32385268","displayGroupId":"7","eventGroupId":"84240","eventGroupName":"MLB","name":"BOS Red Sox @ NY Yankees","nameIdentifier":"BOS Red Sox @ NY Yankees","startDate":"2025-06-06T23:05:00.0000000Z","teamName1":"BOS Red Sox","teamName2":"NY Yankees","teamShortName1":"BOS","teamShortName2":"NYY","team1":{"teamId":29976,"name":"BOS Red Sox","shortName":"BOS"},"team2":{"teamId":29825,"name":"NY Yankees","shortName":"NYY"},"eventStatus":{"state":"NOT_STARTED","isClockDisabled":false,"minute":0,"second":0,"isClockRunning":false},"eventScorecard":{"scorecardComponentId":1},"mediaList":[{"mediaProviderName":"BetRadarStats","mediaId":"55312009","mediaTypeName":"Stats","metadata":{},"updatedAt":"2025-06-06T05:43:48.5548912Z"},{"mediaProviderName":"BetRadarV3","mediaId":"55312009","mediaTypeName":"MatchTracker","metadata":{"betRadarCoverage":"3"},"updatedAt":"2025-06-06T05:43:48.5548912Z"},{"mediaProviderName":"BetRadarV3","mediaId":"55312009","mediaTypeName":"Scoreboard","metadata":{"betRadarCoverage":"3"},"updatedAt":"2025-06-06T05:43:48.5548912Z"}],"liveBettingOffered":false,"liveBettingEnabled":false,"tags":["FeaturedSubcategory","Flashbet","MatchTracker","PrePack","ProgressiveParlayEligible","ProgressiveParlayTeamEligible","SGP","Scoreboard","SgpDynamicOdds","Stats","YourBetEligible"],"flashBetOfferCount":0,"eventAttributes":{"homeTeamStartingPitcherName":"Will Warren","awayTeamStartingPitcherName":"Walker Buehler"},"eventMetadata":{"participantMetadata":{"homeTeamStartingPitcherPlayerId":"181457","awayTeamStartingPitcherPlayerId":"109571","homeTeamStartingPitcherName":"Will Warren","awayTeamStartingPitcherName":"Walker Buehler"},"mediaMetadata":{"BetRadarStats_Stats":{},"BetRadarV3_MatchTracker":{},"BetRadarV3_Scoreboard":{}}}},{"eventId":"32385271","displayGroupId":"7","eventGroupId":"84240","eventGroupName":"MLB","name":"ARI Diamondbacks @ CIN Reds","nameIdentifier":"ARI Diamondbacks @ CIN Reds","startDate":"2025-06-06T23:10:00.0000000Z","teamName1":"ARI Diamondbacks","teamName2":"CIN Reds","teamShortName1":"ARI","teamShortName2":"CIN","team1":{"teamId":29934,"name":"ARI Diamondbacks","shortName":"ARI"},"team2":{"teamId":29919,"name":"CIN Reds","shortName":"CIN"},"eventStatus":{"state":"NOT_STARTED","isClockDisabled":false,"minute":0,"second":0,"isClockRunning":false},"eventScorecard":{"scorecardComponentId":1},"mediaList":[{"mediaProviderName":"BetRadarStats","mediaId":"55309751","mediaTypeName":"Stats","metadata":{},"updatedAt":"2025-06-06T06:07:46.9959282Z"},{"mediaProviderName":"BetRadarV3","mediaId":"55309751","mediaTypeName":"MatchTracker","metadata":{"betRadarCoverage":"3"},"updatedAt":"2025-06-06T06:07:46.9959282Z"},{"mediaProviderName":"BetRadarV3","mediaId":"55309751","mediaTypeName":"Scoreboard","metadata":{"betRadarCoverage":"3"},"updatedAt":"2025-06-06T06:07:46.9959282Z"}],"liveBettingOffered":false,"liveBettingEnabled":false,"tags":["FeaturedSubcategory","Flashbet","MatchTracker","PrePack","ProgressiveParlayEligible","ProgressiveParlayTeamEligible","SGP","Scoreboard","SgpDynamicOdds","Stats","YourBetEligible"],"flashBetOfferCount":0,"eventAttributes":{"homeTeamStartingPitcherName":"Nick Lodolo","awayTeamStartingPitcherName":"Eduardo Rodriguez"},"eventMetadata":{"participantMetadata":{"homeTeamStartingPitcherPlayerId":"105915","awayTeamStartingPitcherPlayerId":"107771","homeTeamStartingPitcherName":"Nick Lodolo","awayTeamStartingPitcherName":"Eduardo Rodriguez"},"mediaMetadata":{"BetRadarStats_Stats":{},"BetRadarV3_MatchTracker":{},"BetRadarV3_Scoreboard":{}}}},{"eventId":"32385277","displayGroupId":"7","eventGroupId":"84240","eventGroupName":"MLB","name":"HOU Astros @ CLE Guardians","nameIdentifier":"HOU Astros @ CLE Guardians","startDate":"2025-06-06T23:10:00.0000000Z","teamName1":"HOU Astros","teamName2":"CLE Guardians","teamShortName1":"HOU","teamShortName2":"CLE","team1":{"teamId":29882,"name":"HOU Astros","shortName":"HOU"},"team2":{"teamId":29913,"name":"CLE Guardians","shortName":"CLE"},"eventStatus":{"state":"NOT_STARTED","isClockDisabled":false,"minute":0,"second":0,"isClockRunning":false},"eventScorecard":{"scorecardComponentId":1},"mediaList":[{"mediaProviderName":"BetRadarStats","mediaId":"55310333","mediaTypeName":"Stats","metadata":{},"updatedAt":"2025-06-06T06:08:22.3419813Z"},{"mediaProviderName":"BetRadarV3","mediaId":"55310333","mediaTypeName":"MatchTracker","metadata":{"betRadarCoverage":"3"},"updatedAt":"2025-06-06T06:08:22.3419813Z"},{"mediaProviderName":"BetRadarV3","mediaId":"55310333","mediaTypeName":"Scoreboard","metadata":{"betRadarCoverage":"3"},"updatedAt":"2025-06-06T06:08:22.3419813Z"}],"liveBettingOffered":false,"liveBettingEnabled":false,"tags":["FeaturedSubcategory","Flashbet","MatchTracker","PrePack","ProgressiveParlayEligible","ProgressiveParlayTeamEligible","SGP","Scoreboard","SgpDynamicOdds","Stats","YourBetEligible"],"flashBetOfferCount":0,"eventAttributes":{"homeTeamStartingPitcherName":"Logan Allen (CLE)","awayTeamStartingPitcherName":"Colton Gordon"},"eventMetadata":{"participantMetadata":{"homeTeamStartingPitcherPlayerId":"161818","awayTeamStartingPitcherPlayerId":"197273","homeTeamStartingPitcherName":"Logan Allen (CLE)","awayTeamStartingPitcherName":"Colton Gordon"},"mediaMetadata":{"BetRadarStats_Stats":{},"BetRadarV3_MatchTracker":{},"BetRadarV3_Scoreboard":{}}}},{"eventId":"32385281","displayGroupId":"7","eventGroupId":"84240","eventGroupName":"MLB","name":"KC Royals @ CHI White Sox","nameIdentifier":"KC Royals @ CHI White Sox","startDate":"2025-06-06T23:40:00.0000000Z","teamName1":"KC Royals","teamName2":"CHI White Sox","teamShortName1":"KC","teamShortName2":"CWS","team1":{"teamId":29965,"name":"KC Royals","shortName":"KC"},"team2":{"teamId":29970,"name":"CHI White Sox","shortName":"CWS"},"eventStatus":{"state":"NOT_STARTED","isClockDisabled":false,"minute":0,"second":0,"isClockRunning":false},"eventScorecard":{"scorecardComponentId":1},"mediaList":[{"mediaProviderName":"BetRadarStats","mediaId":"55311729","mediaTypeName":"Stats","metadata":{},"updatedAt":"2025-06-06T05:40:34.5695274Z"},{"mediaProviderName":"BetRadarV3","mediaId":"55311729","mediaTypeName":"MatchTracker","metadata":{"betRadarCoverage":"3"},"updatedAt":"2025-06-06T05:40:34.5695274Z"},{"mediaProviderName":"BetRadarV3","mediaId":"55311729","mediaTypeName":"Scoreboard","metadata":{"betRadarCoverage":"3"},"updatedAt":"2025-06-06T05:40:34.5695274Z"}],"liveBettingOffered":false,"liveBettingEnabled":false,"tags":["FeaturedSubcategory","Flashbet","MatchTracker","PrePack","ProgressiveParlayEligible","ProgressiveParlayTeamEligible","SGP","Scoreboard","SgpDynamicOdds","Stats","YourBetEligible"],"flashBetOfferCount":0,"eventAttributes":{"homeTeamStartingPitcherName":"Davis Martin","awayTeamStartingPitcherName":"Seth Lugo"},"eventMetadata":{"participantMetadata":{"homeTeamStartingPitcherPlayerId":"152904","awayTeamStartingPitcherPlayerId":"108337","homeTeamStartingPitcherName":"Davis Martin","awayTeamStartingPitcherName":"Seth Lugo"},"mediaMetadata":{"BetRadarStats_Stats":{},"BetRadarV3_MatchTracker":{},"BetRadarV3_Scoreboard":{}}}},{"eventId":"32385286","displayGroupId":"7","eventGroupId":"84240","eventGroupName":"MLB","name":"SD Padres @ MIL Brewers","nameIdentifier":"SD Padres @ MIL Brewers","startDate":"2025-06-07T00:10:00.0000000Z","teamName1":"SD Padres","teamName2":"MIL Brewers","teamShortName1":"SD","teamShortName2":"MIL","team1":{"teamId":29942,"name":"SD Padres","shortName":"SD"},"team2":{"teamId":29847,"name":"MIL Brewers","shortName":"MIL"},"eventStatus":{"state":"NOT_STARTED","isClockDisabled":false,"minute":0,"second":0,"isClockRunning":false},"eventScorecard":{"scorecardComponentId":1},"mediaList":[{"mediaProviderName":"BetRadarStats","mediaId":"55308005","mediaTypeName":"Stats","metadata":{},"updatedAt":"2025-06-06T06:30:35.1718681Z"},{"mediaProviderName":"BetRadarV3","mediaId":"55308005","mediaTypeName":"MatchTracker","metadata":{"betRadarCoverage":"3"},"updatedAt":"2025-06-06T06:30:35.1718681Z"},{"mediaProviderName":"BetRadarV3","mediaId":"55308005","mediaTypeName":"Scoreboard","metadata":{"betRadarCoverage":"3"},"updatedAt":"2025-06-06T06:30:35.1718681Z"}],"liveBettingOffered":false,"liveBettingEnabled":false,"tags":["FeaturedSubcategory","Flashbet","MatchTracker","PrePack","ProgressiveParlayTeamEligible","SGP","Scoreboard","SgpDynamicOdds","Stats","YourBetEligible"],"flashBetOfferCount":0,"eventAttributes":{"homeTeamStartingPitcherName":"Chad Patrick","awayTeamStartingPitcherName":"Randy Vasquez"},"eventMetadata":{"participantMetadata":{"homeTeamStartingPitcherPlayerId":"197284","awayTeamStartingPitcherPlayerId":"160752","homeTeamStartingPitcherName":"Chad Patrick","awayTeamStartingPitcherName":"Randy Vasquez"},"mediaMetadata":{"BetRadarStats_Stats":{},"BetRadarV3_MatchTracker":{},"BetRadarV3_Scoreboard":{}}}},{"eventId":"32385293","displayGroupId":"7","eventGroupId":"84240","eventGroupName":"MLB","name":"LA Dodgers @ STL Cardinals","nameIdentifier":"LA Dodgers @ STL Cardinals","startDate":"2025-06-07T00:15:00.0000000Z","teamName1":"LA Dodgers","teamName2":"STL Cardinals","teamShortName1":"LAD","teamShortName2":"STL","team1":{"teamId":29931,"name":"LA Dodgers","shortName":"LAD"},"team2":{"teamId":29851,"name":"STL Cardinals","shortName":"STL"},"eventStatus":{"state":"NOT_STARTED","isClockDisabled":false,"minute":0,"second":0,"isClockRunning":false},"eventScorecard":{"scorecardComponentId":1},"mediaList":[{"mediaProviderName":"BetRadarStats","mediaId":"55308543","mediaTypeName":"Stats","metadata":{},"updatedAt":"2025-06-06T06:18:19.1002266Z"},{"mediaProviderName":"BetRadarV3","mediaId":"55308543","mediaTypeName":"MatchTracker","metadata":{"betRadarCoverage":"3"},"updatedAt":"2025-06-06T06:18:19.1002266Z"},{"mediaProviderName":"BetRadarV3","mediaId":"55308543","mediaTypeName":"Scoreboard","metadata":{"betRadarCoverage":"3"},"updatedAt":"2025-06-06T06:18:19.1002266Z"}],"liveBettingOffered":false,"liveBettingEnabled":false,"tags":["FeaturedSubcategory","Flashbet","MatchTracker","PrePack","ProgressiveParlayEligible","ProgressiveParlayTeamEligible","SGP","Scoreboard","SgpDynamicOdds","Stats","YourBetEligible"],"flashBetOfferCount":0,"eventAttributes":{"homeTeamStartingPitcherName":"Sonny Gray","awayTeamStartingPitcherName":"Justin Wrobleski"},"eventMetadata":{"participantMetadata":{"homeTeamStartingPitcherPlayerId":"109296","awayTeamStartingPitcherPlayerId":"181117","homeTeamStartingPitcherName":"Sonny Gray","awayTeamStartingPitcherName":"Justin Wrobleski"},"mediaMetadata":{"BetRadarStats_Stats":{},"BetRadarV3_MatchTracker":{},"BetRadarV3_Scoreboard":{}}}},{"eventId":"32385297","displayGroupId":"7","eventGroupId":"84240","eventGroupName":"MLB","name":"NY Mets @ COL Rockies","nameIdentifier":"NY Mets @ COL Rockies","startDate":"2025-06-07T00:40:00.0000000Z","teamName1":"NY Mets","teamName2":"COL Rockies","teamShortName1":"NYM","teamShortName2":"COL","team1":{"teamId":29840,"name":"NY Mets","shortName":"NYM"},"team2":{"teamId":29957,"name":"COL Rockies","shortName":"COL"},"eventStatus":{"state":"NOT_STARTED","isClockDisabled":false,"minute":0,"second":0,"isClockRunning":false},"eventScorecard":{"scorecardComponentId":1},"mediaList":[{"mediaProviderName":"BetRadarStats","mediaId":"55311961","mediaTypeName":"Stats","metadata":{},"updatedAt":"2025-06-06T05:46:45.0265653Z"},{"mediaProviderName":"BetRadarV3","mediaId":"55311961","mediaTypeName":"MatchTracker","metadata":{"betRadarCoverage":"3"},"updatedAt":"2025-06-06T05:46:45.0265653Z"},{"mediaProviderName":"BetRadarV3","mediaId":"55311961","mediaTypeName":"Scoreboard","metadata":{"betRadarCoverage":"3"},"updatedAt":"2025-06-06T05:46:45.0265653Z"}],"liveBettingOffered":false,"liveBettingEnabled":false,"tags":["FeaturedSubcategory","Flashbet","MatchTracker","PrePack","ProgressiveParlayEligible","ProgressiveParlayTeamEligible","SGP","Scoreboard","SgpDynamicOdds","Stats","YourBetEligible"],"flashBetOfferCount":0,"eventAttributes":{"homeTeamStartingPitcherName":"Antonio Senzatela","awayTeamStartingPitcherName":"Kodai Senga"},"eventMetadata":{"participantMetadata":{"homeTeamStartingPitcherPlayerId":"109462","awayTeamStartingPitcherPlayerId":"160790","homeTeamStartingPitcherName":"Antonio Senzatela","awayTeamStartingPitcherName":"Kodai Senga"},"mediaMetadata":{"BetRadarStats_Stats":{},"BetRadarV3_MatchTracker":{},"BetRadarV3_Scoreboard":{}}}},{"eventId":"32385322","displayGroupId":"7","eventGroupId":"84240","eventGroupName":"MLB","name":"SEA Mariners @ LA Angels","nameIdentifier":"SEA Mariners @ LA Angels","startDate":"2025-06-07T01:38:00.0000000Z","teamName1":"SEA Mariners","teamName2":"LA Angels","teamShortName1":"SEA","teamShortName2":"LAA","team1":{"teamId":29815,"name":"SEA Mariners","shortName":"SEA"},"team2":{"teamId":29901,"name":"LA Angels","shortName":"LAA"},"eventStatus":{"state":"NOT_STARTED","isClockDisabled":false,"minute":0,"second":0,"isClockRunning":false},"eventScorecard":{"scorecardComponentId":1},"mediaList":[{"mediaProviderName":"BetRadarStats","mediaId":"55312171","mediaTypeName":"Stats","metadata":{},"updatedAt":"2025-06-06T05:48:13.2624412Z"},{"mediaProviderName":"BetRadarV3","mediaId":"55312171","mediaTypeName":"MatchTracker","metadata":{"betRadarCoverage":"3"},"updatedAt":"2025-06-06T05:48:13.2624412Z"},{"mediaProviderName":"BetRadarV3","mediaId":"55312171","mediaTypeName":"Scoreboard","metadata":{"betRadarCoverage":"3"},"updatedAt":"2025-06-06T05:48:13.2624412Z"}],"liveBettingOffered":false,"liveBettingEnabled":false,"tags":["FeaturedSubcategory","Flashbet","MatchTracker","PrePack","ProgressiveParlayEligible","ProgressiveParlayTeamEligible","SGP","Scoreboard","SgpDynamicOdds","Stats","YourBetEligible"],"flashBetOfferCount":0,"eventAttributes":{"homeTeamStartingPitcherName":"Kyle Hendricks","awayTeamStartingPitcherName":"Bryce Miller"},"eventMetadata":{"participantMetadata":{"homeTeamStartingPitcherPlayerId":"109229","awayTeamStartingPitcherPlayerId":"161892","homeTeamStartingPitcherName":"Kyle Hendricks","awayTeamStartingPitcherName":"Bryce Miller"},"mediaMetadata":{"BetRadarStats_Stats":{},"BetRadarV3_MatchTracker":{},"BetRadarV3_Scoreboard":{}}}},{"eventId":"32385324","displayGroupId":"7","eventGroupId":"84240","eventGroupName":"MLB","name":"ATL Braves @ SF Giants","nameIdentifier":"ATL Braves @ SF Giants","startDate":"2025-06-07T02:15:00.0000000Z","teamName1":"ATL Braves","teamName2":"SF Giants","teamShortName1":"ATL","teamShortName2":"SFG","team1":{"teamId":29861,"name":"ATL Braves","shortName":"ATL"},"team2":{"teamId":29945,"name":"SF Giants","shortName":"SFG"},"eventStatus":{"state":"NOT_STARTED","isClockDisabled":false,"minute":0,"second":0,"isClockRunning":false},"eventScorecard":{"scorecardComponentId":1},"mediaList":[{"mediaProviderName":"BetRadarStats","mediaId":"55307577","mediaTypeName":"Stats","metadata":{},"updatedAt":"2025-06-06T05:50:52.2217322Z"},{"mediaProviderName":"BetRadarV3","mediaId":"55307577","mediaTypeName":"MatchTracker","metadata":{"betRadarCoverage":"3"},"updatedAt":"2025-06-06T05:50:52.2217322Z"},{"mediaProviderName":"BetRadarV3","mediaId":"55307577","mediaTypeName":"Scoreboard","metadata":{"betRadarCoverage":"3"},"updatedAt":"2025-06-06T05:50:52.2217322Z"}],"liveBettingOffered":false,"liveBettingEnabled":false,"tags":["FeaturedSubcategory","Flashbet","MatchTracker","PrePack","ProgressiveParlayEligible","ProgressiveParlayTeamEligible","SGP","Scoreboard","SgpDynamicOdds","Stats","YourBetEligible"],"flashBetOfferCount":0,"eventAttributes":{"homeTeamStartingPitcherName":"Hayden Birdsong","awayTeamStartingPitcherName":"Spencer Schwellenbach"},"eventMetadata":{"participantMetadata":{"homeTeamStartingPitcherPlayerId":"181037","awayTeamStartingPitcherPlayerId":"180195","homeTeamStartingPitcherName":"Hayden Birdsong","awayTeamStartingPitcherName":"Spencer Schwellenbach"},"mediaMetadata":{"BetRadarStats_Stats":{},"BetRadarV3_MatchTracker":{},"BetRadarV3_Scoreboard":{}}}}],"tags":["FeaturedSubcategory","Flashbet","MatchTracker","PrePack","ProgressiveParlayEligible","ProgressiveParlayTeamEligible","SGP","Scoreboard","SgpDynamicOdds","Stats","YourBetEligible"],"nameIdentifier":"MLB"}}