{"eventGroup":{"eventGroupId":"84240","displayGroupId":"7","name":"MLB","offerCategories":[{"offerCategoryId":493,"name":"Game Lines","offerSubcategoryDescriptors":[{"subcategoryId":4519,"name":"Game","offerSubcategory":{"name":"Game","subcategoryId":4519,"componentId":210,"tags":["SGP"],"offers":[[{"providerOfferId":"2_76015568","eventId":"30822892","eventGroupId":"84240","label":"Run Line","isSuspended":false,"isOpen":true,"offerSubcategoryId":4519,"isSubcategoryFeatured":true,"betOfferTypeId":1,"providerCriterionId":"2_0","outcomes":[{"providerOutcomeId":"0HC76015568P150_3","providerId":2,"providerOfferId":"2_76015568","label":"MIL Brewers","oddsAmerican":"-155","oddsDecimal":1.6451613,"oddsDecimalDisplay":"1.64","oddsFractional":"20/31","line":1.5,"participant":"MIL Brewers","participantType":"Team","main":true,"sortOrder":1499,"tags":["MainPointLine","SGP"],"participants":[{"id":"29847","name":"MIL Brewers","type":"Team"}]},{"providerOutcomeId":"0HC76015568N150_1","providerId":2,"providerOfferId":"2_76015568","label":"MIN Twins","oddsAmerican":"\u002B130","oddsDecimal":2.3,"oddsDecimalDisplay":"2.30","oddsFractional":"13/10","line":-1.5,"participant":"MIN Twins","participantType":"Team","main":true,"sortOrder":1501,"tags":["MainPointLine","SGP"],"participants":[{"id":"29909","name":"MIN Twins","type":"Team"}]}],"offerSequence":0,"source":"5","displayGroupId":"7","main":true,"tags":["PrimaryMarket","SGP","YourBetEligible","Cashout","FeaturedSubcategory","Default"]},{"providerOfferId":"3_76015568","eventId":"30822892","eventGroupId":"84240","label":"Total","isSuspended":false,"isOpen":true,"offerSubcategoryId":4519,"isSubcategoryFeatured":true,"betOfferTypeId":6,"providerCriterionId":"3_0","outcomes":[{"providerOutcomeId":"0OU76015568O800_1","providerId":2,"providerOfferId":"3_76015568","label":"Over","oddsAmerican":"-115","oddsDecimal":1.86956522,"oddsDecimalDisplay":"1.86","oddsFractional":"20/23","line":8,"participant":"","participantType":"Unknown","main":true,"sortOrder":8000,"tags":["MainPointLine","SGP"]},{"providerOutcomeId":"0OU76015568U800_3","providerId":2,"providerOfferId":"3_76015568","label":"Under","oddsAmerican":"-105","oddsDecimal":1.95238096,"oddsDecimalDisplay":"1.95","oddsFractional":"20/21","line":8,"participant":"","participantType":"Unknown","main":true,"sortOrder":8002,"tags":["MainPointLine","SGP"]}],"offerSequence":0,"source":"5","displayGroupId":"7","main":true,"tags":["PrimaryMarket","SGP","YourBetEligible","Cashout","FeaturedSubcategory","Default"]},{"providerOfferId":"1_76015568","eventId":"30822892","eventGroupId":"84240","label":"Moneyline","isSuspended":false,"isOpen":true,"offerSubcategoryId":4519,"isSubcategoryFeatured":true,"betOfferTypeId":2,"providerCriterionId":"1_0","outcomes":[{"providerOutcomeId":"0ML76015568_3","providerId":2,"providerOfferId":"1_76015568","label":"MIL Brewers","oddsAmerican":"\u002B136","oddsDecimal":2.36,"oddsDecimalDisplay":"2.36","oddsFractional":"34/25","participant":"MIL Brewers","participantType":"Team","main":true,"sortOrder":1206938758,"tags":["SGP"],"participants":[{"id":"29847","name":"MIL Brewers","type":"Team"}]},{"providerOutcomeId":"0ML76015568_1","providerId":2,"providerOfferId":"1_76015568","label":"MIN Twins","oddsAmerican":"-162","oddsDecimal":1.61728396,"oddsDecimalDisplay":"1.61","oddsFractional":"50/81","participant":"MIN Twins","participantType":"Team","main":true,"sortOrder":1206940754,"tags":["SGP"],"participants":[{"id":"29909","name":"MIN Twins","type":"Team"}]}],"offerSequence":0,"source":"5","displayGroupId":"7","main":true,"tags":["PrimaryMarket","SGP","YourBetEligible","Cashout","FeaturedSubcategory","Default"]}],[{"providerOfferId":"2_76015573","eventId":"30822896","eventGroupId":"84240","label":"Run Line","isSuspended":false,"isOpen":true,"offerSubcategoryId":4519,"isSubcategoryFeatured":true,"betOfferTypeId":1,"providerCriterionId":"2_0","outcomes":[{"providerOutcomeId":"0HC76015573N150_3","providerId":2,"providerOfferId":"2_76015573","label":"PHI Phillies","oddsAmerican":"\u002B110","oddsDecimal":2.1,"oddsDecimalDisplay":"2.10","oddsFractional":"11/10","line":-1.5,"participant":"PHI Phillies","participantType":"Team","main":true,"sortOrder":-1501,"tags":["MainPointLine","SGP"],"participants":[{"id":"29857","name":"PHI Phillies","type":"Team"}]},{"providerOutcomeId":"0HC76015573P150_1","providerId":2,"providerOfferId":"2_76015573","label":"PIT Pirates","oddsAmerican":"-130","oddsDecimal":1.76923077,"oddsDecimalDisplay":"1.76","oddsFractional":"10/13","line":1.5,"participant":"PIT Pirates","participantType":"Team","main":true,"sortOrder":-1499,"tags":["MainPointLine","SGP"],"participants":[{"id":"29924","name":"PIT Pirates","type":"Team"}]}],"offerSequence":0,"source":"5","displayGroupId":"7","main":true,"tags":["PrimaryMarket","SGP","YourBetEligible","Cashout","FeaturedSubcategory","Default"]},{"providerOfferId":"3_76015573","eventId":"30822896","eventGroupId":"84240","label":"Total","isSuspended":false,"isOpen":true,"offerSubcategoryId":4519,"isSubcategoryFeatured":true,"betOfferTypeId":6,"providerCriterionId":"3_0","outcomes":[{"providerOutcomeId":"0OU76015573O900_1","providerId":2,"providerOfferId":"3_76015573","label":"Over","oddsAmerican":"-118","oddsDecimal":1.84745763,"oddsDecimalDisplay":"1.84","oddsFractional":"50/59","line":9,"participant":"","participantType":"Unknown","main":true,"sortOrder":9000,"tags":["MainPointLine","SGP"]},{"providerOutcomeId":"0OU76015573U900_3","providerId":2,"providerOfferId":"3_76015573","label":"Under","oddsAmerican":"-102","oddsDecimal":1.98039216,"oddsDecimalDisplay":"1.98","oddsFractional":"50/51","line":9,"participant":"","participantType":"Unknown","main":true,"sortOrder":9002,"tags":["MainPointLine","SGP"]}],"offerSequence":0,"source":"5","displayGroupId":"7","main":true,"tags":["PrimaryMarket","SGP","YourBetEligible","Cashout","FeaturedSubcategory","Default"]},{"providerOfferId":"1_76015573","eventId":"30822896","eventGroupId":"84240","label":"Moneyline","isSuspended":false,"isOpen":true,"offerSubcategoryId":4519,"isSubcategoryFeatured":true,"betOfferTypeId":2,"providerCriterionId":"1_0","outcomes":[{"providerOutcomeId":"0ML76015573_3","providerId":2,"providerOfferId":"1_76015573","label":"PHI Phillies","oddsAmerican":"-142","oddsDecimal":1.70422536,"oddsDecimalDisplay":"1.70","oddsFractional":"50/71","participant":"PHI Phillies","participantType":"Team","main":true,"sortOrder":1206938793,"tags":["SGP"],"participants":[{"id":"29857","name":"PHI Phillies","type":"Team"}]},{"providerOutcomeId":"0ML76015573_1","providerId":2,"providerOfferId":"1_76015573","label":"PIT Pirates","oddsAmerican":"\u002B120","oddsDecimal":2.2,"oddsDecimalDisplay":"2.20","oddsFractional":"6/5","participant":"PIT Pirates","participantType":"Team","main":true,"sortOrder":1206940789,"tags":["SGP"],"participants":[{"id":"29924","name":"PIT Pirates","type":"Team"}]}],"offerSequence":0,"source":"5","displayGroupId":"7","main":true,"tags":["PrimaryMarket","SGP","YourBetEligible","Cashout","FeaturedSubcategory","Default"]}],[{"providerOfferId":"2_76015644","eventId":"30822932","eventGroupId":"84240","label":"Run Line","isSuspended":false,"isOpen":true,"offerSubcategoryId":4519,"isSubcategoryFeatured":true,"betOfferTypeId":1,"providerCriterionId":"2_0","outcomes":[{"providerOutcomeId":"0HC76015644P150_3","providerId":2,"providerOfferId":"2_76015644","label":"TB Rays","oddsAmerican":"-155","oddsDecimal":1.6451613,"oddsDecimalDisplay":"1.64","oddsFractional":"20/31","line":1.5,"participant":"TB Rays","participantType":"Team","main":true,"sortOrder":1499,"tags":["MainPointLine","SGP"],"participants":[{"id":"29880","name":"TB Rays","type":"Team"}]},{"providerOutcomeId":"0HC76015644N150_1","providerId":2,"providerOfferId":"2_76015644","label":"NY Yankees","oddsAmerican":"\u002B130","oddsDecimal":2.3,"oddsDecimalDisplay":"2.30","oddsFractional":"13/10","line":-1.5,"participant":"NY Yankees","participantType":"Team","main":true,"sortOrder":1501,"tags":["MainPointLine","SGP"],"participants":[{"id":"29825","name":"NY Yankees","type":"Team"}]}],"offerSequence":0,"source":"5","displayGroupId":"7","main":true,"tags":["PrimaryMarket","SGP","YourBetEligible","Cashout","FeaturedSubcategory","Default"]},{"providerOfferId":"3_76015644","eventId":"30822932","eventGroupId":"84240","label":"Total","isSuspended":false,"isOpen":true,"offerSubcategoryId":4519,"isSubcategoryFeatured":true,"betOfferTypeId":6,"providerCriterionId":"3_0","outcomes":[{"providerOutcomeId":"0OU76015644O850_1","providerId":2,"providerOfferId":"3_76015644","label":"Over","oddsAmerican":"-120","oddsDecimal":1.83333334,"oddsDecimalDisplay":"1.83","oddsFractional":"5/6","line":8.5,"participant":"","participantType":"Unknown","main":true,"sortOrder":8500,"tags":["MainPointLine","SGP"]},{"providerOutcomeId":"0OU76015644U850_3","providerId":2,"providerOfferId":"3_76015644","label":"Under","oddsAmerican":"\u002B100","oddsDecimal":2,"oddsDecimalDisplay":"2.00","oddsFractional":"1/1","line":8.5,"participant":"","participantType":"Unknown","main":true,"sortOrder":8502,"tags":["MainPointLine","SGP"]}],"offerSequence":0,"source":"5","displayGroupId":"7","main":true,"tags":["PrimaryMarket","SGP","YourBetEligible","Cashout","FeaturedSubcategory","Default"]},{"providerOfferId":"1_76015644","eventId":"30822932","eventGroupId":"84240","label":"Moneyline","isSuspended":false,"isOpen":true,"offerSubcategoryId":4519,"isSubcategoryFeatured":true,"betOfferTypeId":2,"providerCriterionId":"1_0","outcomes":[{"providerOutcomeId":"0ML76015644_3","providerId":2,"providerOfferId":"1_76015644","label":"TB Rays","oddsAmerican":"\u002B136","oddsDecimal":2.36,"oddsDecimalDisplay":"2.36","oddsFractional":"34/25","participant":"TB Rays","participantType":"Team","main":true,"sortOrder":1206939927,"tags":["SGP"],"participants":[{"id":"29880","name":"TB Rays","type":"Team"}]},{"providerOutcomeId":"0ML76015644_1","providerId":2,"providerOfferId":"1_76015644","label":"NY Yankees","oddsAmerican":"-162","oddsDecimal":1.61728396,"oddsDecimalDisplay":"1.61","oddsFractional":"50/81","participant":"NY Yankees","participantType":"Team","main":true,"sortOrder":1206941923,"tags":["SGP"],"participants":[{"id":"29825","name":"NY Yankees","type":"Team"}]}],"offerSequence":0,"source":"5","displayGroupId":"7","main":true,"tags":["PrimaryMarket","SGP","YourBetEligible","Cashout","FeaturedSubcategory","Default"]}],[{"providerOfferId":"2_76015574","eventId":"30822897","eventGroupId":"84240","label":"Run Line","isSuspended":false,"isOpen":true,"offerSubcategoryId":4519,"isSubcategoryFeatured":true,"betOfferTypeId":1,"providerCriterionId":"2_0","outcomes":[{"providerOutcomeId":"0HC76015574N150_3","providerId":2,"providerOfferId":"2_76015574","label":"CIN Reds","oddsAmerican":"\u002B154","oddsDecimal":2.54,"oddsDecimalDisplay":"2.54","oddsFractional":"77/50","line":-1.5,"participant":"CIN Reds","participantType":"Team","main":true,"sortOrder":-1501,"tags":["MainPointLine","SGP"],"participants":[{"id":"29919","name":"CIN Reds","type":"Team"}]},{"providerOutcomeId":"0HC76015574P150_1","providerId":2,"providerOfferId":"2_76015574","label":"WAS Nationals","oddsAmerican":"-185","oddsDecimal":1.54054055,"oddsDecimalDisplay":"1.54","oddsFractional":"20/37","line":1.5,"participant":"WAS Nationals","participantType":"Team","main":true,"sortOrder":-1499,"tags":["MainPointLine","SGP"],"participants":[{"id":"29836","name":"WAS Nationals","type":"Team"}]}],"offerSequence":0,"source":"5","displayGroupId":"7","main":true,"tags":["PrimaryMarket","SGP","YourBetEligible","Cashout","FeaturedSubcategory","Default"]},{"providerOfferId":"3_76015574","eventId":"30822897","eventGroupId":"84240","label":"Total","isSuspended":false,"isOpen":true,"offerSubcategoryId":4519,"isSubcategoryFeatured":true,"betOfferTypeId":6,"providerCriterionId":"3_0","outcomes":[{"providerOutcomeId":"0OU76015574O900_1","providerId":2,"providerOfferId":"3_76015574","label":"Over","oddsAmerican":"\u002B100","oddsDecimal":2,"oddsDecimalDisplay":"2.00","oddsFractional":"1/1","line":9,"participant":"","participantType":"Unknown","main":true,"sortOrder":9000,"tags":["MainPointLine","SGP"]},{"providerOutcomeId":"0OU76015574U900_3","providerId":2,"providerOfferId":"3_76015574","label":"Under","oddsAmerican":"-120","oddsDecimal":1.83333334,"oddsDecimalDisplay":"1.83","oddsFractional":"5/6","line":9,"participant":"","participantType":"Unknown","main":true,"sortOrder":9002,"tags":["MainPointLine","SGP"]}],"offerSequence":0,"source":"5","displayGroupId":"7","main":true,"tags":["PrimaryMarket","SGP","YourBetEligible","Cashout","FeaturedSubcategory","Default"]},{"providerOfferId":"1_76015574","eventId":"30822897","eventGroupId":"84240","label":"Moneyline","isSuspended":false,"isOpen":true,"offerSubcategoryId":4519,"isSubcategoryFeatured":true,"betOfferTypeId":2,"providerCriterionId":"1_0","outcomes":[{"providerOutcomeId":"0ML76015574_3","providerId":2,"providerOfferId":"1_76015574","label":"CIN Reds","oddsAmerican":"-108","oddsDecimal":1.92592593,"oddsDecimalDisplay":"1.92","oddsFractional":"25/27","participant":"CIN Reds","participantType":"Team","main":true,"sortOrder":1206938800,"tags":["SGP"],"participants":[{"id":"29919","name":"CIN Reds","type":"Team"}]},{"providerOutcomeId":"0ML76015574_1","providerId":2,"providerOfferId":"1_76015574","label":"WAS Nationals","oddsAmerican":"-112","oddsDecimal":1.89285715,"oddsDecimalDisplay":"1.89","oddsFractional":"25/28","participant":"WAS Nationals","participantType":"Team","main":true,"sortOrder":1206940796,"tags":["SGP"],"participants":[{"id":"29836","name":"WAS Nationals","type":"Team"}]}],"offerSequence":0,"source":"5","displayGroupId":"7","main":true,"tags":["PrimaryMarket","SGP","YourBetEligible","Cashout","FeaturedSubcategory","Default"]}],[{"providerOfferId":"2_76015569","eventId":"30822893","eventGroupId":"84240","label":"Run Line","isSuspended":false,"isOpen":true,"offerSubcategoryId":4519,"isSubcategoryFeatured":true,"betOfferTypeId":1,"providerCriterionId":"2_0","outcomes":[{"providerOutcomeId":"0HC76015569P150_3","providerId":2,"providerOfferId":"2_76015569","label":"STL Cardinals","oddsAmerican":"-166","oddsDecimal":1.60240964,"oddsDecimalDisplay":"1.60","oddsFractional":"50/83","line":1.5,"participant":"STL Cardinals","participantType":"Team","main":true,"sortOrder":1499,"tags":["MainPointLine","SGP"],"participants":[{"id":"29851","name":"STL Cardinals","type":"Team"}]},{"providerOutcomeId":"0HC76015569N150_1","providerId":2,"providerOfferId":"2_76015569","label":"ATL Braves","oddsAmerican":"\u002B140","oddsDecimal":2.4,"oddsDecimalDisplay":"2.40","oddsFractional":"7/5","line":-1.5,"participant":"ATL Braves","participantType":"Team","main":true,"sortOrder":1501,"tags":["MainPointLine","SGP"],"participants":[{"id":"29861","name":"ATL Braves","type":"Team"}]}],"offerSequence":0,"source":"5","displayGroupId":"7","main":true,"tags":["PrimaryMarket","SGP","YourBetEligible","Cashout","FeaturedSubcategory","Default"]},{"providerOfferId":"3_76015569","eventId":"30822893","eventGroupId":"84240","label":"Total","isSuspended":false,"isOpen":true,"offerSubcategoryId":4519,"isSubcategoryFeatured":true,"betOfferTypeId":6,"providerCriterionId":"3_0","outcomes":[{"providerOutcomeId":"0OU76015569O850_1","providerId":2,"providerOfferId":"3_76015569","label":"Over","oddsAmerican":"-115","oddsDecimal":1.86956522,"oddsDecimalDisplay":"1.86","oddsFractional":"20/23","line":8.5,"participant":"","participantType":"Unknown","main":true,"sortOrder":8500,"tags":["MainPointLine","SGP"]},{"providerOutcomeId":"0OU76015569U850_3","providerId":2,"providerOfferId":"3_76015569","label":"Under","oddsAmerican":"-105","oddsDecimal":1.95238096,"oddsDecimalDisplay":"1.95","oddsFractional":"20/21","line":8.5,"participant":"","participantType":"Unknown","main":true,"sortOrder":8502,"tags":["MainPointLine","SGP"]}],"offerSequence":0,"source":"5","displayGroupId":"7","main":true,"tags":["PrimaryMarket","SGP","YourBetEligible","Cashout","FeaturedSubcategory","Default"]},{"providerOfferId":"1_76015569","eventId":"30822893","eventGroupId":"84240","label":"Moneyline","isSuspended":false,"isOpen":true,"offerSubcategoryId":4519,"isSubcategoryFeatured":true,"betOfferTypeId":2,"providerCriterionId":"1_0","outcomes":[{"providerOutcomeId":"0ML76015569_3","providerId":2,"providerOfferId":"1_76015569","label":"STL Cardinals","oddsAmerican":"\u002B120","oddsDecimal":2.2,"oddsDecimalDisplay":"2.20","oddsFractional":"6/5","participant":"STL Cardinals","participantType":"Team","main":true,"sortOrder":1206938765,"tags":["SGP"],"participants":[{"id":"29851","name":"STL Cardinals","type":"Team"}]},{"providerOutcomeId":"0ML76015569_1","providerId":2,"providerOfferId":"1_76015569","label":"ATL Braves","oddsAmerican":"-142","oddsDecimal":1.70422536,"oddsDecimalDisplay":"1.70","oddsFractional":"50/71","participant":"ATL Braves","participantType":"Team","main":true,"sortOrder":1206940761,"tags":["SGP"],"participants":[{"id":"29861","name":"ATL Braves","type":"Team"}]}],"offerSequence":0,"source":"5","displayGroupId":"7","main":true,"tags":["PrimaryMarket","SGP","YourBetEligible","Cashout","FeaturedSubcategory","Default"]}],[{"providerOfferId":"2_76015583","eventId":"30822902","eventGroupId":"84240","label":"Run Line","isSuspended":false,"isOpen":true,"offerSubcategoryId":4519,"isSubcategoryFeatured":true,"betOfferTypeId":1,"providerCriterionId":"2_0","outcomes":[{"providerOutcomeId":"0HC76015583P150_3","providerId":2,"providerOfferId":"2_76015583","label":"DET Tigers","oddsAmerican":"-155","oddsDecimal":1.6451613,"oddsDecimalDisplay":"1.64","oddsFractional":"20/31","line":1.5,"participant":"DET Tigers","participantType":"Team","main":true,"sortOrder":1499,"tags":["MainPointLine","SGP"],"participants":[{"id":"29871","name":"DET Tigers","type":"Team"}]},{"providerOutcomeId":"0HC76015583N150_1","providerId":2,"providerOfferId":"2_76015583","label":"TOR Blue Jays","oddsAmerican":"\u002B130","oddsDecimal":2.3,"oddsDecimalDisplay":"2.30","oddsFractional":"13/10","line":-1.5,"participant":"TOR Blue Jays","participantType":"Team","main":true,"sortOrder":1501,"tags":["MainPointLine","SGP"],"participants":[{"id":"29868","name":"TOR Blue Jays","type":"Team"}]}],"offerSequence":0,"source":"5","displayGroupId":"7","main":true,"tags":["PrimaryMarket","SGP","YourBetEligible","Cashout","FeaturedSubcategory","Default"]},{"providerOfferId":"3_76015583","eventId":"30822902","eventGroupId":"84240","label":"Total","isSuspended":false,"isOpen":true,"offerSubcategoryId":4519,"isSubcategoryFeatured":true,"betOfferTypeId":6,"providerCriterionId":"3_0","outcomes":[{"providerOutcomeId":"0OU76015583O800_1","providerId":2,"providerOfferId":"3_76015583","label":"Over","oddsAmerican":"-115","oddsDecimal":1.86956522,"oddsDecimalDisplay":"1.86","oddsFractional":"20/23","line":8,"participant":"","participantType":"Unknown","main":true,"sortOrder":8000,"tags":["MainPointLine","SGP"]},{"providerOutcomeId":"0OU76015583U800_3","providerId":2,"providerOfferId":"3_76015583","label":"Under","oddsAmerican":"-105","oddsDecimal":1.95238096,"oddsDecimalDisplay":"1.95","oddsFractional":"20/21","line":8,"participant":"","participantType":"Unknown","main":true,"sortOrder":8002,"tags":["MainPointLine","SGP"]}],"offerSequence":0,"source":"5","displayGroupId":"7","main":true,"tags":["PrimaryMarket","SGP","YourBetEligible","Cashout","FeaturedSubcategory","Default"]},{"providerOfferId":"1_76015583","eventId":"30822902","eventGroupId":"84240","label":"Moneyline","isSuspended":false,"isOpen":true,"offerSubcategoryId":4519,"isSubcategoryFeatured":true,"betOfferTypeId":2,"providerCriterionId":"1_0","outcomes":[{"providerOutcomeId":"0ML76015583_3","providerId":2,"providerOfferId":"1_76015583","label":"DET Tigers","oddsAmerican":"\u002B136","oddsDecimal":2.36,"oddsDecimalDisplay":"2.36","oddsFractional":"34/25","participant":"DET Tigers","participantType":"Team","main":true,"sortOrder":1206938905,"tags":["SGP"],"participants":[{"id":"29871","name":"DET Tigers","type":"Team"}]},{"providerOutcomeId":"0ML76015583_1","providerId":2,"providerOfferId":"1_76015583","label":"TOR Blue Jays","oddsAmerican":"-162","oddsDecimal":1.61728396,"oddsDecimalDisplay":"1.61","oddsFractional":"50/81","participant":"TOR Blue Jays","participantType":"Team","main":true,"sortOrder":1206940901,"tags":["SGP"],"participants":[{"id":"29868","name":"TOR Blue Jays","type":"Team"}]}],"offerSequence":0,"source":"5","displayGroupId":"7","main":true,"tags":["PrimaryMarket","SGP","YourBetEligible","Cashout","FeaturedSubcategory","Default"]}],[{"providerOfferId":"2_76015656","eventId":"30822939","eventGroupId":"84240","label":"Run Line","isSuspended":false,"isOpen":true,"offerSubcategoryId":4519,"isSubcategoryFeatured":true,"betOfferTypeId":1,"providerCriterionId":"2_0","outcomes":[{"providerOutcomeId":"0HC76015656N150_3","providerId":2,"providerOfferId":"2_76015656","label":"NY Mets","oddsAmerican":"\u002B110","oddsDecimal":2.1,"oddsDecimalDisplay":"2.10","oddsFractional":"11/10","line":-1.5,"participant":"NY Mets","participantType":"Team","main":true,"sortOrder":-1501,"tags":["MainPointLine","SGP"],"participants":[{"id":"29840","name":"NY Mets","type":"Team"}]},{"providerOutcomeId":"0HC76015656P150_1","providerId":2,"providerOfferId":"2_76015656","label":"MIA Marlins","oddsAmerican":"-130","oddsDecimal":1.76923077,"oddsDecimalDisplay":"1.76","oddsFractional":"10/13","line":1.5,"participant":"MIA Marlins","participantType":"Team","main":true,"sortOrder":-1499,"tags":["MainPointLine","SGP"],"participants":[{"id":"29953","name":"MIA Marlins","type":"Team"}]}],"offerSequence":0,"source":"5","displayGroupId":"7","main":true,"tags":["PrimaryMarket","SGP","YourBetEligible","Cashout","FeaturedSubcategory","Default"]},{"providerOfferId":"3_76015656","eventId":"30822939","eventGroupId":"84240","label":"Total","isSuspended":false,"isOpen":true,"offerSubcategoryId":4519,"isSubcategoryFeatured":true,"betOfferTypeId":6,"providerCriterionId":"3_0","outcomes":[{"providerOutcomeId":"0OU76015656O850_1","providerId":2,"providerOfferId":"3_76015656","label":"Over","oddsAmerican":"-112","oddsDecimal":1.89285715,"oddsDecimalDisplay":"1.89","oddsFractional":"25/28","line":8.5,"participant":"","participantType":"Unknown","main":true,"sortOrder":8500,"tags":["MainPointLine","SGP"]},{"providerOutcomeId":"0OU76015656U850_3","providerId":2,"providerOfferId":"3_76015656","label":"Under","oddsAmerican":"-108","oddsDecimal":1.92592593,"oddsDecimalDisplay":"1.92","oddsFractional":"25/27","line":8.5,"participant":"","participantType":"Unknown","main":true,"sortOrder":8502,"tags":["MainPointLine","SGP"]}],"offerSequence":0,"source":"5","displayGroupId":"7","main":true,"tags":["PrimaryMarket","SGP","YourBetEligible","Cashout","FeaturedSubcategory","Default"]},{"providerOfferId":"1_76015656","eventId":"30822939","eventGroupId":"84240","label":"Moneyline","isSuspended":false,"isOpen":true,"offerSubcategoryId":4519,"isSubcategoryFeatured":true,"betOfferTypeId":2,"providerCriterionId":"1_0","outcomes":[{"providerOutcomeId":"0ML76015656_3","providerId":2,"providerOfferId":"1_76015656","label":"NY Mets","oddsAmerican":"-148","oddsDecimal":1.67567568,"oddsDecimalDisplay":"1.67","oddsFractional":"25/37","participant":"NY Mets","participantType":"Team","main":true,"sortOrder":1206940088,"tags":["SGP"],"participants":[{"id":"29840","name":"NY Mets","type":"Team"}]},{"providerOutcomeId":"0ML76015656_1","providerId":2,"providerOfferId":"1_76015656","label":"MIA Marlins","oddsAmerican":"\u002B124","oddsDecimal":2.24,"oddsDecimalDisplay":"2.24","oddsFractional":"31/25","participant":"MIA Marlins","participantType":"Team","main":true,"sortOrder":1206942084,"tags":["SGP"],"participants":[{"id":"29953","name":"MIA Marlins","type":"Team"}]}],"offerSequence":0,"source":"5","displayGroupId":"7","main":true,"tags":["PrimaryMarket","SGP","YourBetEligible","Cashout","FeaturedSubcategory","Default"]}],[{"providerOfferId":"2_76015590","eventId":"30822906","eventGroupId":"84240","label":"Run Line","isSuspended":false,"isOpen":true,"offerSubcategoryId":4519,"isSubcategoryFeatured":true,"betOfferTypeId":1,"providerCriterionId":"2_0","outcomes":[{"providerOutcomeId":"0HC76015590N150_3","providerId":2,"providerOfferId":"2_76015590","label":"SD Padres","oddsAmerican":"\u002B160","oddsDecimal":2.6,"oddsDecimalDisplay":"2.60","oddsFractional":"8/5","line":-1.5,"participant":"SD Padres","participantType":"Team","main":true,"sortOrder":-1501,"tags":["MainPointLine","SGP"],"participants":[{"id":"29942","name":"SD Padres","type":"Team"}]},{"providerOutcomeId":"0HC76015590P150_1","providerId":2,"providerOfferId":"2_76015590","label":"CLE Guardians","oddsAmerican":"-192","oddsDecimal":1.52083334,"oddsDecimalDisplay":"1.52","oddsFractional":"25/48","line":1.5,"participant":"CLE Guardians","participantType":"Team","main":true,"sortOrder":-1499,"tags":["MainPointLine","SGP"],"participants":[{"id":"29913","name":"CLE Guardians","type":"Team"}]}],"offerSequence":0,"source":"5","displayGroupId":"7","main":true,"tags":["PrimaryMarket","SGP","YourBetEligible","Cashout","FeaturedSubcategory","Default"]},{"providerOfferId":"3_76015590","eventId":"30822906","eventGroupId":"84240","label":"Total","isSuspended":false,"isOpen":true,"offerSubcategoryId":4519,"isSubcategoryFeatured":true,"betOfferTypeId":6,"providerCriterionId":"3_0","outcomes":[{"providerOutcomeId":"0OU76015590O800_1","providerId":2,"providerOfferId":"3_76015590","label":"Over","oddsAmerican":"-108","oddsDecimal":1.92592593,"oddsDecimalDisplay":"1.92","oddsFractional":"25/27","line":8,"participant":"","participantType":"Unknown","main":true,"sortOrder":8000,"tags":["MainPointLine","SGP"]},{"providerOutcomeId":"0OU76015590U800_3","providerId":2,"providerOfferId":"3_76015590","label":"Under","oddsAmerican":"-112","oddsDecimal":1.89285715,"oddsDecimalDisplay":"1.89","oddsFractional":"25/28","line":8,"participant":"","participantType":"Unknown","main":true,"sortOrder":8002,"tags":["MainPointLine","SGP"]}],"offerSequence":0,"source":"5","displayGroupId":"7","main":true,"tags":["PrimaryMarket","SGP","YourBetEligible","Cashout","FeaturedSubcategory","Default"]},{"providerOfferId":"1_76015590","eventId":"30822906","eventGroupId":"84240","label":"Moneyline","isSuspended":false,"isOpen":true,"offerSubcategoryId":4519,"isSubcategoryFeatured":true,"betOfferTypeId":2,"providerCriterionId":"1_0","outcomes":[{"providerOutcomeId":"0ML76015590_3","providerId":2,"providerOfferId":"1_76015590","label":"SD Padres","oddsAmerican":"-105","oddsDecimal":1.95238096,"oddsDecimalDisplay":"1.95","oddsFractional":"20/21","participant":"SD Padres","participantType":"Team","main":true,"sortOrder":1206938996,"tags":["SGP"],"participants":[{"id":"29942","name":"SD Padres","type":"Team"}]},{"providerOutcomeId":"0ML76015590_1","providerId":2,"providerOfferId":"1_76015590","label":"CLE Guardians","oddsAmerican":"-115","oddsDecimal":1.86956522,"oddsDecimalDisplay":"1.86","oddsFractional":"20/23","participant":"CLE Guardians","participantType":"Team","main":true,"sortOrder":1206940992,"tags":["SGP"],"participants":[{"id":"29913","name":"CLE Guardians","type":"Team"}]}],"offerSequence":0,"source":"5","displayGroupId":"7","main":true,"tags":["PrimaryMarket","SGP","YourBetEligible","Cashout","FeaturedSubcategory","Default"]}],[{"providerOfferId":"2_76015597","eventId":"30822910","eventGroupId":"84240","label":"Run Line","isSuspended":false,"isOpen":true,"offerSubcategoryId":4519,"isSubcategoryFeatured":true,"betOfferTypeId":1,"providerCriterionId":"2_0","outcomes":[{"providerOutcomeId":"0HC76015597P150_3","providerId":2,"providerOfferId":"2_76015597","label":"CHI White Sox","oddsAmerican":"-110","oddsDecimal":1.90909091,"oddsDecimalDisplay":"1.90","oddsFractional":"10/11","line":1.5,"participant":"CHI White Sox","participantType":"Team","main":true,"sortOrder":1499,"tags":["MainPointLine","SGP"],"participants":[{"id":"29970","name":"CHI White Sox","type":"Team"}]},{"providerOutcomeId":"0HC76015597N150_1","providerId":2,"providerOfferId":"2_76015597","label":"KC Royals","oddsAmerican":"-110","oddsDecimal":1.90909091,"oddsDecimalDisplay":"1.90","oddsFractional":"10/11","line":-1.5,"participant":"KC Royals","participantType":"Team","main":true,"sortOrder":1501,"tags":["MainPointLine","SGP"],"participants":[{"id":"29965","name":"KC Royals","type":"Team"}]}],"offerSequence":0,"source":"5","displayGroupId":"7","main":true,"tags":["PrimaryMarket","SGP","YourBetEligible","Cashout","FeaturedSubcategory","Default"]},{"providerOfferId":"3_76015597","eventId":"30822910","eventGroupId":"84240","label":"Total","isSuspended":false,"isOpen":true,"offerSubcategoryId":4519,"isSubcategoryFeatured":true,"betOfferTypeId":6,"providerCriterionId":"3_0","outcomes":[{"providerOutcomeId":"0OU76015597O850_1","providerId":2,"providerOfferId":"3_76015597","label":"Over","oddsAmerican":"-102","oddsDecimal":1.98039216,"oddsDecimalDisplay":"1.98","oddsFractional":"50/51","line":8.5,"participant":"","participantType":"Unknown","main":true,"sortOrder":8500,"tags":["MainPointLine","SGP"]},{"providerOutcomeId":"0OU76015597U850_3","providerId":2,"providerOfferId":"3_76015597","label":"Under","oddsAmerican":"-118","oddsDecimal":1.84745763,"oddsDecimalDisplay":"1.84","oddsFractional":"50/59","line":8.5,"participant":"","participantType":"Unknown","main":true,"sortOrder":8502,"tags":["MainPointLine","SGP"]}],"offerSequence":0,"source":"5","displayGroupId":"7","main":true,"tags":["PrimaryMarket","SGP","YourBetEligible","Cashout","FeaturedSubcategory","Default"]},{"providerOfferId":"1_76015597","eventId":"30822910","eventGroupId":"84240","label":"Moneyline","isSuspended":false,"isOpen":true,"offerSubcategoryId":4519,"isSubcategoryFeatured":true,"betOfferTypeId":2,"providerCriterionId":"1_0","outcomes":[{"providerOutcomeId":"0ML76015597_3","providerId":2,"providerOfferId":"1_76015597","label":"CHI White Sox","oddsAmerican":"\u002B185","oddsDecimal":2.85,"oddsDecimalDisplay":"2.85","oddsFractional":"37/20","participant":"CHI White Sox","participantType":"Team","main":true,"sortOrder":1206939066,"tags":["SGP"],"participants":[{"id":"29970","name":"CHI White Sox","type":"Team"}]},{"providerOutcomeId":"0ML76015597_1","providerId":2,"providerOfferId":"1_76015597","label":"KC Royals","oddsAmerican":"-225","oddsDecimal":1.44444445,"oddsDecimalDisplay":"1.44","oddsFractional":"4/9","participant":"KC Royals","participantType":"Team","main":true,"sortOrder":1206941062,"tags":["SGP"],"participants":[{"id":"29965","name":"KC Royals","type":"Team"}]}],"offerSequence":0,"source":"5","displayGroupId":"7","main":true,"tags":["PrimaryMarket","SGP","YourBetEligible","Cashout","FeaturedSubcategory","Default"]}],[{"providerOfferId":"2_76015636","eventId":"30822927","eventGroupId":"84240","label":"Run Line","isSuspended":false,"isOpen":true,"offerSubcategoryId":4519,"isSubcategoryFeatured":true,"betOfferTypeId":1,"providerCriterionId":"2_0","outcomes":[{"providerOutcomeId":"0HC76015636P150_3","providerId":2,"providerOfferId":"2_76015636","label":"ARI Diamondbacks","oddsAmerican":"-205","oddsDecimal":1.48780488,"oddsDecimalDisplay":"1.48","oddsFractional":"20/41","line":1.5,"participant":"ARI Diamondbacks","participantType":"Team","main":true,"sortOrder":1499,"tags":["MainPointLine","SGP"],"participants":[{"id":"29934","name":"ARI Diamondbacks","type":"Team"}]},{"providerOutcomeId":"0HC76015636N150_1","providerId":2,"providerOfferId":"2_76015636","label":"CHI Cubs","oddsAmerican":"\u002B170","oddsDecimal":2.7,"oddsDecimalDisplay":"2.70","oddsFractional":"17/10","line":-1.5,"participant":"CHI Cubs","participantType":"Team","main":true,"sortOrder":1501,"tags":["MainPointLine","SGP"],"participants":[{"id":"29894","name":"CHI Cubs","type":"Team"}]}],"offerSequence":0,"source":"5","displayGroupId":"7","main":true,"tags":["PrimaryMarket","SGP","YourBetEligible","Cashout","FeaturedSubcategory","Default"]},{"providerOfferId":"3_76015636","eventId":"30822927","eventGroupId":"84240","label":"Total","isSuspended":false,"isOpen":true,"offerSubcategoryId":4519,"isSubcategoryFeatured":true,"betOfferTypeId":6,"providerCriterionId":"3_0","outcomes":[{"providerOutcomeId":"0OU76015636O750_1","providerId":2,"providerOfferId":"3_76015636","label":"Over","oddsAmerican":"\u002B100","oddsDecimal":2,"oddsDecimalDisplay":"2.00","oddsFractional":"1/1","line":7.5,"participant":"","participantType":"Unknown","main":true,"sortOrder":7500,"tags":["MainPointLine","SGP"]},{"providerOutcomeId":"0OU76015636U750_3","providerId":2,"providerOfferId":"3_76015636","label":"Under","oddsAmerican":"-120","oddsDecimal":1.83333334,"oddsDecimalDisplay":"1.83","oddsFractional":"5/6","line":7.5,"participant":"","participantType":"Unknown","main":true,"sortOrder":7502,"tags":["MainPointLine","SGP"]}],"offerSequence":0,"source":"5","displayGroupId":"7","main":true,"tags":["PrimaryMarket","SGP","YourBetEligible","Cashout","FeaturedSubcategory","Default"]},{"providerOfferId":"1_76015636","eventId":"30822927","eventGroupId":"84240","label":"Moneyline","isSuspended":false,"isOpen":true,"offerSubcategoryId":4519,"isSubcategoryFeatured":true,"betOfferTypeId":2,"providerCriterionId":"1_0","outcomes":[{"providerOutcomeId":"0ML76015636_3","providerId":2,"providerOfferId":"1_76015636","label":"ARI Diamondbacks","oddsAmerican":"\u002B105","oddsDecimal":2.05,"oddsDecimalDisplay":"2.05","oddsFractional":"21/20","participant":"ARI Diamondbacks","participantType":"Team","main":true,"sortOrder":1206939836,"tags":["SGP"],"participants":[{"id":"29934","name":"ARI Diamondbacks","type":"Team"}]},{"providerOutcomeId":"0ML76015636_1","providerId":2,"providerOfferId":"1_76015636","label":"CHI Cubs","oddsAmerican":"-125","oddsDecimal":1.8,"oddsDecimalDisplay":"1.80","oddsFractional":"4/5","participant":"CHI Cubs","participantType":"Team","main":true,"sortOrder":1206941832,"tags":["SGP"],"participants":[{"id":"29894","name":"CHI Cubs","type":"Team"}]}],"offerSequence":0,"source":"5","displayGroupId":"7","main":true,"tags":["PrimaryMarket","SGP","YourBetEligible","Cashout","FeaturedSubcategory","Default"]}],[{"providerOfferId":"2_76015638","eventId":"30822928","eventGroupId":"84240","label":"Run Line","isSuspended":false,"isOpen":true,"offerSubcategoryId":4519,"isSubcategoryFeatured":true,"betOfferTypeId":1,"providerCriterionId":"2_0","outcomes":[{"providerOutcomeId":"0HC76015638N150_3","providerId":2,"providerOfferId":"2_76015638","label":"BAL Orioles","oddsAmerican":"\u002B142","oddsDecimal":2.42,"oddsDecimalDisplay":"2.42","oddsFractional":"71/50","line":-1.5,"participant":"BAL Orioles","participantType":"Team","main":true,"sortOrder":-1501,"tags":["MainPointLine","SGP"],"participants":[{"id":"29829","name":"BAL Orioles","type":"Team"}]},{"providerOutcomeId":"0HC76015638P150_1","providerId":2,"providerOfferId":"2_76015638","label":"TEX Rangers","oddsAmerican":"-170","oddsDecimal":1.5882353,"oddsDecimalDisplay":"1.58","oddsFractional":"10/17","line":1.5,"participant":"TEX Rangers","participantType":"Team","main":true,"sortOrder":-1499,"tags":["MainPointLine","SGP"],"participants":[{"id":"29891","name":"TEX Rangers","type":"Team"}]}],"offerSequence":0,"source":"5","displayGroupId":"7","main":true,"tags":["PrimaryMarket","SGP","YourBetEligible","Cashout","FeaturedSubcategory","Default"]},{"providerOfferId":"3_76015638","eventId":"30822928","eventGroupId":"84240","label":"Total","isSuspended":false,"isOpen":true,"offerSubcategoryId":4519,"isSubcategoryFeatured":true,"betOfferTypeId":6,"providerCriterionId":"3_0","outcomes":[{"providerOutcomeId":"0OU76015638O850_1","providerId":2,"providerOfferId":"3_76015638","label":"Over","oddsAmerican":"-122","oddsDecimal":1.81967214,"oddsDecimalDisplay":"1.81","oddsFractional":"50/61","line":8.5,"participant":"","participantType":"Unknown","main":true,"sortOrder":8500,"tags":["MainPointLine","SGP"]},{"providerOutcomeId":"0OU76015638U850_3","providerId":2,"providerOfferId":"3_76015638","label":"Under","oddsAmerican":"\u002B102","oddsDecimal":2.02,"oddsDecimalDisplay":"2.02","oddsFractional":"51/50","line":8.5,"participant":"","participantType":"Unknown","main":true,"sortOrder":8502,"tags":["MainPointLine","SGP"]}],"offerSequence":0,"source":"5","displayGroupId":"7","main":true,"tags":["PrimaryMarket","SGP","YourBetEligible","Cashout","FeaturedSubcategory","Default"]},{"providerOfferId":"1_76015638","eventId":"30822928","eventGroupId":"84240","label":"Moneyline","isSuspended":false,"isOpen":true,"offerSubcategoryId":4519,"isSubcategoryFeatured":true,"betOfferTypeId":2,"providerCriterionId":"1_0","outcomes":[{"providerOutcomeId":"0ML76015638_3","providerId":2,"providerOfferId":"1_76015638","label":"BAL Orioles","oddsAmerican":"-112","oddsDecimal":1.89285715,"oddsDecimalDisplay":"1.89","oddsFractional":"25/28","participant":"BAL Orioles","participantType":"Team","main":true,"sortOrder":1206939857,"tags":["SGP"],"participants":[{"id":"29829","name":"BAL Orioles","type":"Team"}]},{"providerOutcomeId":"0ML76015638_1","providerId":2,"providerOfferId":"1_76015638","label":"TEX Rangers","oddsAmerican":"-108","oddsDecimal":1.92592593,"oddsDecimalDisplay":"1.92","oddsFractional":"25/27","participant":"TEX Rangers","participantType":"Team","main":true,"sortOrder":1206941853,"tags":["SGP"],"participants":[{"id":"29891","name":"TEX Rangers","type":"Team"}]}],"offerSequence":0,"source":"5","displayGroupId":"7","main":true,"tags":["PrimaryMarket","SGP","YourBetEligible","Cashout","FeaturedSubcategory","Default"]}],[{"providerOfferId":"2_76015643","eventId":"30822931","eventGroupId":"84240","label":"Run Line","isSuspended":false,"isOpen":true,"offerSubcategoryId":4519,"isSubcategoryFeatured":true,"betOfferTypeId":1,"providerCriterionId":"2_0","outcomes":[{"providerOutcomeId":"0HC76015643N150_3","providerId":2,"providerOfferId":"2_76015643","label":"SF Giants","oddsAmerican":"\u002B102","oddsDecimal":2.02,"oddsDecimalDisplay":"2.02","oddsFractional":"51/50","line":-1.5,"participant":"SF Giants","participantType":"Team","main":true,"sortOrder":-1501,"tags":["MainPointLine","SGP"],"participants":[{"id":"29945","name":"SF Giants","type":"Team"}]},{"providerOutcomeId":"0HC76015643P150_1","providerId":2,"providerOfferId":"2_76015643","label":"COL Rockies","oddsAmerican":"-122","oddsDecimal":1.81967214,"oddsDecimalDisplay":"1.81","oddsFractional":"50/61","line":1.5,"participant":"COL Rockies","participantType":"Team","main":true,"sortOrder":-1499,"tags":["MainPointLine","SGP"],"participants":[{"id":"29957","name":"COL Rockies","type":"Team"}]}],"offerSequence":0,"source":"5","displayGroupId":"7","main":true,"tags":["PrimaryMarket","SGP","YourBetEligible","Cashout","FeaturedSubcategory","Default"]},{"providerOfferId":"3_76015643","eventId":"30822931","eventGroupId":"84240","label":"Total","isSuspended":false,"isOpen":true,"offerSubcategoryId":4519,"isSubcategoryFeatured":true,"betOfferTypeId":6,"providerCriterionId":"3_0","outcomes":[{"providerOutcomeId":"0OU76015643O1050_1","providerId":2,"providerOfferId":"3_76015643","label":"Over","oddsAmerican":"-115","oddsDecimal":1.86956522,"oddsDecimalDisplay":"1.86","oddsFractional":"20/23","line":10.5,"participant":"","participantType":"Unknown","main":true,"sortOrder":10500,"tags":["MainPointLine","SGP"]},{"providerOutcomeId":"0OU76015643U1050_3","providerId":2,"providerOfferId":"3_76015643","label":"Under","oddsAmerican":"-105","oddsDecimal":1.95238096,"oddsDecimalDisplay":"1.95","oddsFractional":"20/21","line":10.5,"participant":"","participantType":"Unknown","main":true,"sortOrder":10502,"tags":["MainPointLine","SGP"]}],"offerSequence":0,"source":"5","displayGroupId":"7","main":true,"tags":["PrimaryMarket","SGP","YourBetEligible","Cashout","FeaturedSubcategory","Default"]},{"providerOfferId":"1_76015643","eventId":"30822931","eventGroupId":"84240","label":"Moneyline","isSuspended":false,"isOpen":true,"offerSubcategoryId":4519,"isSubcategoryFeatured":true,"betOfferTypeId":2,"providerCriterionId":"1_0","outcomes":[{"providerOutcomeId":"0ML76015643_3","providerId":2,"providerOfferId":"1_76015643","label":"SF Giants","oddsAmerican":"-148","oddsDecimal":1.67567568,"oddsDecimalDisplay":"1.67","oddsFractional":"25/37","participant":"SF Giants","participantType":"Team","main":true,"sortOrder":1206939920,"tags":["SGP"],"participants":[{"id":"29945","name":"SF Giants","type":"Team"}]},{"providerOutcomeId":"0ML76015643_1","providerId":2,"providerOfferId":"1_76015643","label":"COL Rockies","oddsAmerican":"\u002B124","oddsDecimal":2.24,"oddsDecimalDisplay":"2.24","oddsFractional":"31/25","participant":"COL Rockies","participantType":"Team","main":true,"sortOrder":1206941916,"tags":["SGP"],"participants":[{"id":"29957","name":"COL Rockies","type":"Team"}]}],"offerSequence":0,"source":"5","displayGroupId":"7","main":true,"tags":["PrimaryMarket","SGP","YourBetEligible","Cashout","FeaturedSubcategory","Default"]}],[{"providerOfferId":"2_76015645","eventId":"30822933","eventGroupId":"84240","label":"Run Line","isSuspended":false,"isOpen":true,"offerSubcategoryId":4519,"isSubcategoryFeatured":true,"betOfferTypeId":1,"providerCriterionId":"2_0","outcomes":[{"providerOutcomeId":"0HC76015645P150_3","providerId":2,"providerOfferId":"2_76015645","label":"LA Angels","oddsAmerican":"-180","oddsDecimal":1.55555556,"oddsDecimalDisplay":"1.55","oddsFractional":"5/9","line":1.5,"participant":"LA Angels","participantType":"Team","main":true,"sortOrder":1499,"tags":["MainPointLine","SGP"],"participants":[{"id":"29901","name":"LA Angels","type":"Team"}]},{"providerOutcomeId":"0HC76015645N150_1","providerId":2,"providerOfferId":"2_76015645","label":"OAK Athletics","oddsAmerican":"\u002B150","oddsDecimal":2.5,"oddsDecimalDisplay":"2.50","oddsFractional":"6/4","line":-1.5,"participant":"OAK Athletics","participantType":"Team","main":true,"sortOrder":1501,"tags":["MainPointLine","SGP"],"participants":[{"id":"29811","name":"OAK Athletics","type":"Team"}]}],"offerSequence":0,"source":"5","displayGroupId":"7","main":true,"tags":["PrimaryMarket","SGP","YourBetEligible","Cashout","FeaturedSubcategory","Default"]},{"providerOfferId":"3_76015645","eventId":"30822933","eventGroupId":"84240","label":"Total","isSuspended":false,"isOpen":true,"offerSubcategoryId":4519,"isSubcategoryFeatured":true,"betOfferTypeId":6,"providerCriterionId":"3_0","outcomes":[{"providerOutcomeId":"0OU76015645O850_1","providerId":2,"providerOfferId":"3_76015645","label":"Over","oddsAmerican":"-120","oddsDecimal":1.83333334,"oddsDecimalDisplay":"1.83","oddsFractional":"5/6","line":8.5,"participant":"","participantType":"Unknown","main":true,"sortOrder":8500,"tags":["MainPointLine","SGP"]},{"providerOutcomeId":"0OU76015645U850_3","providerId":2,"providerOfferId":"3_76015645","label":"Under","oddsAmerican":"\u002B100","oddsDecimal":2,"oddsDecimalDisplay":"2.00","oddsFractional":"1/1","line":8.5,"participant":"","participantType":"Unknown","main":true,"sortOrder":8502,"tags":["MainPointLine","SGP"]}],"offerSequence":0,"source":"5","displayGroupId":"7","main":true,"tags":["PrimaryMarket","SGP","YourBetEligible","Cashout","FeaturedSubcategory","Default"]},{"providerOfferId":"1_76015645","eventId":"30822933","eventGroupId":"84240","label":"Moneyline","isSuspended":false,"isOpen":true,"offerSubcategoryId":4519,"isSubcategoryFeatured":true,"betOfferTypeId":2,"providerCriterionId":"1_0","outcomes":[{"providerOutcomeId":"0ML76015645_3","providerId":2,"providerOfferId":"1_76015645","label":"LA Angels","oddsAmerican":"\u002B114","oddsDecimal":2.14,"oddsDecimalDisplay":"2.14","oddsFractional":"57/50","participant":"LA Angels","participantType":"Team","main":true,"sortOrder":1206939934,"tags":["SGP"],"participants":[{"id":"29901","name":"LA Angels","type":"Team"}]},{"providerOutcomeId":"0ML76015645_1","providerId":2,"providerOfferId":"1_76015645","label":"OAK Athletics","oddsAmerican":"-135","oddsDecimal":1.74074075,"oddsDecimalDisplay":"1.74","oddsFractional":"20/27","participant":"OAK Athletics","participantType":"Team","main":true,"sortOrder":1206941930,"tags":["SGP"],"participants":[{"id":"29811","name":"OAK Athletics","type":"Team"}]}],"offerSequence":0,"source":"5","displayGroupId":"7","main":true,"tags":["PrimaryMarket","SGP","YourBetEligible","Cashout","FeaturedSubcategory","Default"]}],[{"providerOfferId":"2_76015657","eventId":"30822940","eventGroupId":"84240","label":"Run Line","isSuspended":false,"isOpen":true,"offerSubcategoryId":4519,"isSubcategoryFeatured":true,"betOfferTypeId":1,"providerCriterionId":"2_0","outcomes":[{"providerOutcomeId":"0HC76015657N150_3","providerId":2,"providerOfferId":"2_76015657","label":"HOU Astros","oddsAmerican":"\u002B160","oddsDecimal":2.6,"oddsDecimalDisplay":"2.60","oddsFractional":"8/5","line":-1.5,"participant":"HOU Astros","participantType":"Team","main":true,"sortOrder":-1501,"tags":["MainPointLine","SGP"],"participants":[{"id":"29882","name":"HOU Astros","type":"Team"}]},{"providerOutcomeId":"0HC76015657P150_1","providerId":2,"providerOfferId":"2_76015657","label":"SEA Mariners","oddsAmerican":"-192","oddsDecimal":1.52083334,"oddsDecimalDisplay":"1.52","oddsFractional":"25/48","line":1.5,"participant":"SEA Mariners","participantType":"Team","main":true,"sortOrder":-1499,"tags":["MainPointLine","SGP"],"participants":[{"id":"29815","name":"SEA Mariners","type":"Team"}]}],"offerSequence":0,"source":"5","displayGroupId":"7","main":true,"tags":["PrimaryMarket","SGP","YourBetEligible","Cashout","FeaturedSubcategory","Default"]},{"providerOfferId":"3_76015657","eventId":"30822940","eventGroupId":"84240","label":"Total","isSuspended":false,"isOpen":true,"offerSubcategoryId":4519,"isSubcategoryFeatured":true,"betOfferTypeId":6,"providerCriterionId":"3_0","outcomes":[{"providerOutcomeId":"0OU76015657O700_1","providerId":2,"providerOfferId":"3_76015657","label":"Over","oddsAmerican":"-120","oddsDecimal":1.83333334,"oddsDecimalDisplay":"1.83","oddsFractional":"5/6","line":7,"participant":"","participantType":"Unknown","main":true,"sortOrder":7000,"tags":["MainPointLine","SGP"]},{"providerOutcomeId":"0OU76015657U700_3","providerId":2,"providerOfferId":"3_76015657","label":"Under","oddsAmerican":"\u002B100","oddsDecimal":2,"oddsDecimalDisplay":"2.00","oddsFractional":"1/1","line":7,"participant":"","participantType":"Unknown","main":true,"sortOrder":7002,"tags":["MainPointLine","SGP"]}],"offerSequence":0,"source":"5","displayGroupId":"7","main":true,"tags":["PrimaryMarket","SGP","YourBetEligible","Cashout","FeaturedSubcategory","Default"]},{"providerOfferId":"1_76015657","eventId":"30822940","eventGroupId":"84240","label":"Moneyline","isSuspended":false,"isOpen":true,"offerSubcategoryId":4519,"isSubcategoryFeatured":true,"betOfferTypeId":2,"providerCriterionId":"1_0","outcomes":[{"providerOutcomeId":"0ML76015657_3","providerId":2,"providerOfferId":"1_76015657","label":"HOU Astros","oddsAmerican":"-105","oddsDecimal":1.95238096,"oddsDecimalDisplay":"1.95","oddsFractional":"20/21","participant":"HOU Astros","participantType":"Team","main":true,"sortOrder":1206940095,"tags":["SGP"],"participants":[{"id":"29882","name":"HOU Astros","type":"Team"}]},{"providerOutcomeId":"0ML76015657_1","providerId":2,"providerOfferId":"1_76015657","label":"SEA Mariners","oddsAmerican":"-115","oddsDecimal":1.86956522,"oddsDecimalDisplay":"1.86","oddsFractional":"20/23","participant":"SEA Mariners","participantType":"Team","main":true,"sortOrder":1206942091,"tags":["SGP"],"participants":[{"id":"29815","name":"SEA Mariners","type":"Team"}]}],"offerSequence":0,"source":"5","displayGroupId":"7","main":true,"tags":["PrimaryMarket","SGP","YourBetEligible","Cashout","FeaturedSubcategory","Default"]}],[{"providerOfferId":"2_76015660","eventId":"30822943","eventGroupId":"84240","label":"Run Line","isSuspended":false,"isOpen":true,"offerSubcategoryId":4519,"isSubcategoryFeatured":true,"betOfferTypeId":1,"providerCriterionId":"2_0","outcomes":[{"providerOutcomeId":"0HC76015660N150_3","providerId":2,"providerOfferId":"2_76015660","label":"BOS Red Sox","oddsAmerican":"\u002B164","oddsDecimal":2.64,"oddsDecimalDisplay":"2.64","oddsFractional":"41/25","line":-1.5,"participant":"BOS Red Sox","participantType":"Team","main":true,"sortOrder":-1501,"tags":["MainPointLine","SGP"],"participants":[{"id":"29976","name":"BOS Red Sox","type":"Team"}]},{"providerOutcomeId":"0HC76015660P150_1","providerId":2,"providerOfferId":"2_76015660","label":"LA Dodgers","oddsAmerican":"-198","oddsDecimal":1.50505051,"oddsDecimalDisplay":"1.50","oddsFractional":"50/99","line":1.5,"participant":"LA Dodgers","participantType":"Team","main":true,"sortOrder":-1499,"tags":["MainPointLine","SGP"],"participants":[{"id":"29931","name":"LA Dodgers","type":"Team"}]}],"offerSequence":0,"source":"5","displayGroupId":"7","main":true,"tags":["PrimaryMarket","SGP","YourBetEligible","Cashout","FeaturedSubcategory","Default"]},{"providerOfferId":"3_76015660","eventId":"30822943","eventGroupId":"84240","label":"Total","isSuspended":false,"isOpen":true,"offerSubcategoryId":4519,"isSubcategoryFeatured":true,"betOfferTypeId":6,"providerCriterionId":"3_0","outcomes":[{"providerOutcomeId":"0OU76015660O900_1","providerId":2,"providerOfferId":"3_76015660","label":"Over","oddsAmerican":"-102","oddsDecimal":1.98039216,"oddsDecimalDisplay":"1.98","oddsFractional":"50/51","line":9,"participant":"","participantType":"Unknown","main":true,"sortOrder":9000,"tags":["MainPointLine","SGP"]},{"providerOutcomeId":"0OU76015660U900_3","providerId":2,"providerOfferId":"3_76015660","label":"Under","oddsAmerican":"-118","oddsDecimal":1.84745763,"oddsDecimalDisplay":"1.84","oddsFractional":"50/59","line":9,"participant":"","participantType":"Unknown","main":true,"sortOrder":9002,"tags":["MainPointLine","SGP"]}],"offerSequence":0,"source":"5","displayGroupId":"7","main":true,"tags":["PrimaryMarket","SGP","YourBetEligible","Cashout","FeaturedSubcategory","Default"]},{"providerOfferId":"1_76015660","eventId":"30822943","eventGroupId":"84240","label":"Moneyline","isSuspended":false,"isOpen":true,"offerSubcategoryId":4519,"isSubcategoryFeatured":true,"betOfferTypeId":2,"providerCriterionId":"1_0","outcomes":[{"providerOutcomeId":"0ML76015660_3","providerId":2,"providerOfferId":"1_76015660","label":"BOS Red Sox","oddsAmerican":"\u002B102","oddsDecimal":2.02,"oddsDecimalDisplay":"2.02","oddsFractional":"51/50","participant":"BOS Red Sox","participantType":"Team","main":true,"sortOrder":1206940116,"tags":["SGP"],"participants":[{"id":"29976","name":"BOS Red Sox","type":"Team"}]},{"providerOutcomeId":"0ML76015660_1","providerId":2,"providerOfferId":"1_76015660","label":"LA Dodgers","oddsAmerican":"-122","oddsDecimal":1.81967214,"oddsDecimalDisplay":"1.81","oddsFractional":"50/61","participant":"LA Dodgers","participantType":"Team","main":true,"sortOrder":1206942112,"tags":["SGP"],"participants":[{"id":"29931","name":"LA Dodgers","type":"Team"}]}],"offerSequence":0,"source":"5","displayGroupId":"7","main":true,"tags":["PrimaryMarket","SGP","YourBetEligible","Cashout","FeaturedSubcategory","Default"]}]]},"tags":["SGP"]},{"subcategoryId":13168,"name":"Alternate Run Line","tags":["SGP"]},{"subcategoryId":13169,"name":"Alternate Total Runs","tags":["SGP"]},{"subcategoryId":6618,"name":"Listed Pitcher"},{"subcategoryId":6694,"name":"Total Runs (3-Way)"}],"tags":["SGP"]},{"offerCategoryId":743,"name":"Batter Props","tags":["SGP"]},{"offerCategoryId":1031,"name":"Pitcher Props","tags":["SGP"]},{"offerCategoryId":988,"name":"Plate Appearance"},{"offerCategoryId":1024,"name":"1st Inning","tags":["SGP"]},{"offerCategoryId":1626,"name":"1st X Innings","tags":["SGP"]},{"offerCategoryId":729,"name":"Innings","tags":["SGP"]},{"offerCategoryId":724,"name":"Game Props","tags":["SGP"]},{"offerCategoryId":1133,"name":"Correct Score"},{"offerCategoryId":754,"name":"Game Parlays"},{"offerCategoryId":517,"name":"Team Futures"},{"offerCategoryId":684,"name":"Awards"},{"offerCategoryId":1279,"name":"Player Season Specials"},{"offerCategoryId":1297,"name":"League Seeding"},{"offerCategoryId":972,"name":"Season Specials"}],"events":[{"eventId":"30822892","displayGroupId":"7","eventGroupId":"84240","eventGroupName":"MLB","name":"MIL Brewers @ MIN Twins","nameIdentifier":"MIL Brewers @ MIN Twins","startDate":"2024-07-21T17:05:00.0000000Z","teamName1":"MIL Brewers","teamName2":"MIN Twins","teamShortName1":"MIL","teamShortName2":"MIN","team1":{"teamId":29847,"name":"MIL Brewers","shortName":"MIL"},"team2":{"teamId":29909,"name":"MIN Twins","shortName":"MIN"},"eventStatus":{"state":"NOT_STARTED","isClockDisabled":false,"minute":0,"second":0,"isClockRunning":false},"eventScorecard":{"scorecardComponentId":1},"mediaList":[{"mediaProviderName":"BetRadarStats","mediaId":"46681327","mediaTypeName":"Stats","metadata":{},"updatedAt":"2024-07-21T11:52:42.2036170Z"},{"mediaProviderName":"BetRadarV3","mediaId":"46681327","mediaTypeName":"MatchTracker","metadata":{"betRadarCoverage":"3"},"updatedAt":"2024-07-21T11:52:42.2036170Z"},{"mediaProviderName":"BetRadarV3","mediaId":"46681327","mediaTypeName":"Scoreboard","metadata":{"betRadarCoverage":"3"},"updatedAt":"2024-07-21T11:52:42.2036170Z"}],"liveBettingOffered":false,"liveBettingEnabled":false,"tags":["FeaturedSubcategory","Flashbet","MatchTracker","PrePack","ProgressiveParlayEligible","SGP","Scoreboard","SgpDynamicOdds","Stats","YourBetEligible"],"flashBetOfferCount":0,"eventAttributes":{"homeTeamStartingPitcherName":"Joe Ryan","awayTeamStartingPitcherName":"Aaron Civale"},"eventMetadata":{"participantMetadata":{"homeTeamStartingPitcherPlayerId":"106137","awayTeamStartingPitcherPlayerId":"108322","homeTeamStartingPitcherName":"Joe Ryan","awayTeamStartingPitcherName":"Aaron Civale"},"mediaMetadata":{"BetRadarStats_Stats":{},"BetRadarV3_MatchTracker":{},"BetRadarV3_Scoreboard":{}}}},{"eventId":"30822896","displayGroupId":"7","eventGroupId":"84240","eventGroupName":"MLB","name":"PHI Phillies @ PIT Pirates","nameIdentifier":"PHI Phillies @ PIT Pirates","startDate":"2024-07-21T17:35:00.0000000Z","teamName1":"PHI Phillies","teamName2":"PIT Pirates","teamShortName1":"PHI","teamShortName2":"PIT","team1":{"teamId":29857,"name":"PHI Phillies","shortName":"PHI"},"team2":{"teamId":29924,"name":"PIT Pirates","shortName":"PIT"},"eventStatus":{"state":"NOT_STARTED","isClockDisabled":false,"minute":0,"second":0,"isClockRunning":false},"eventScorecard":{"scorecardComponentId":1},"mediaList":[{"mediaProviderName":"BetRadarStats","mediaId":"46682439","mediaTypeName":"Stats","metadata":{},"updatedAt":"2024-07-21T12:03:30.7855836Z"},{"mediaProviderName":"BetRadarV3","mediaId":"46682439","mediaTypeName":"MatchTracker","metadata":{"betRadarCoverage":"3"},"updatedAt":"2024-07-21T12:03:30.7855836Z"},{"mediaProviderName":"BetRadarV3","mediaId":"46682439","mediaTypeName":"Scoreboard","metadata":{"betRadarCoverage":"3"},"updatedAt":"2024-07-21T12:03:30.7855836Z"}],"liveBettingOffered":false,"liveBettingEnabled":false,"tags":["FeaturedSubcategory","Flashbet","MatchTracker","PrePack","ProgressiveParlayEligible","SGP","Scoreboard","SgpDynamicOdds","Stats","YourBetEligible"],"flashBetOfferCount":0,"eventAttributes":{"homeTeamStartingPitcherName":"Marco Gonzales","awayTeamStartingPitcherName":"Tyler Phillips"},"eventMetadata":{"participantMetadata":{"homeTeamStartingPitcherPlayerId":"107866","awayTeamStartingPitcherPlayerId":"106897","homeTeamStartingPitcherName":"Marco Gonzales","awayTeamStartingPitcherName":"Tyler Phillips"},"mediaMetadata":{"BetRadarStats_Stats":{},"BetRadarV3_MatchTracker":{},"BetRadarV3_Scoreboard":{}}}},{"eventId":"30822932","displayGroupId":"7","eventGroupId":"84240","eventGroupName":"MLB","name":"TB Rays @ NY Yankees","nameIdentifier":"TB Rays @ NY Yankees","startDate":"2024-07-21T17:35:00.0000000Z","teamName1":"TB Rays","teamName2":"NY Yankees","teamShortName1":"TB","teamShortName2":"NYY","team1":{"teamId":29880,"name":"TB Rays","shortName":"TB"},"team2":{"teamId":29825,"name":"NY Yankees","shortName":"NYY"},"eventStatus":{"state":"NOT_STARTED","isClockDisabled":false,"minute":0,"second":0,"isClockRunning":false},"eventScorecard":{"scorecardComponentId":1},"mediaList":[{"mediaProviderName":"BetRadarStats","mediaId":"46682575","mediaTypeName":"Stats","metadata":{},"updatedAt":"2024-07-21T12:13:59.2926959Z"},{"mediaProviderName":"BetRadarV3","mediaId":"46682575","mediaTypeName":"MatchTracker","metadata":{"betRadarCoverage":"3"},"updatedAt":"2024-07-21T12:13:59.2926959Z"},{"mediaProviderName":"BetRadarV3","mediaId":"46682575","mediaTypeName":"Scoreboard","metadata":{"betRadarCoverage":"3"},"updatedAt":"2024-07-21T12:13:59.2926959Z"}],"liveBettingOffered":false,"liveBettingEnabled":false,"tags":["FeaturedSubcategory","Flashbet","MatchTracker","PrePack","ProgressiveParlayEligible","SGP","Scoreboard","SgpDynamicOdds","Stats","YourBetEligible"],"flashBetOfferCount":0,"eventAttributes":{"homeTeamStartingPitcherName":"Marcus Stroman","awayTeamStartingPitcherName":"Shane Baz"},"eventMetadata":{"participantMetadata":{"homeTeamStartingPitcherPlayerId":"108243","awayTeamStartingPitcherPlayerId":"107973","homeTeamStartingPitcherName":"Marcus Stroman","awayTeamStartingPitcherName":"Shane Baz"},"mediaMetadata":{"BetRadarStats_Stats":{},"BetRadarV3_MatchTracker":{},"BetRadarV3_Scoreboard":{}}}},{"eventId":"30822897","displayGroupId":"7","eventGroupId":"84240","eventGroupName":"MLB","name":"CIN Reds @ WAS Nationals","nameIdentifier":"CIN Reds @ WAS Nationals","startDate":"2024-07-21T17:35:00.0000000Z","teamName1":"CIN Reds","teamName2":"WAS Nationals","teamShortName1":"CIN","teamShortName2":"WAS","team1":{"teamId":29919,"name":"CIN Reds","shortName":"CIN"},"team2":{"teamId":29836,"name":"WAS Nationals","shortName":"WAS"},"eventStatus":{"state":"NOT_STARTED","isClockDisabled":false,"minute":0,"second":0,"isClockRunning":false},"eventScorecard":{"scorecardComponentId":1},"mediaList":[{"mediaProviderName":"BetRadarStats","mediaId":"46685019","mediaTypeName":"Stats","metadata":{},"updatedAt":"2024-07-21T11:58:50.4334002Z"},{"mediaProviderName":"BetRadarV3","mediaId":"46685019","mediaTypeName":"MatchTracker","metadata":{"betRadarCoverage":"3"},"updatedAt":"2024-07-21T11:58:50.4334002Z"},{"mediaProviderName":"BetRadarV3","mediaId":"46685019","mediaTypeName":"Scoreboard","metadata":{"betRadarCoverage":"3"},"updatedAt":"2024-07-21T11:58:50.4334002Z"}],"liveBettingOffered":false,"liveBettingEnabled":false,"tags":["FeaturedSubcategory","Flashbet","MatchTracker","PrePack","ProgressiveParlayEligible","SGP","Scoreboard","SgpDynamicOdds","Stats","YourBetEligible"],"flashBetOfferCount":0,"eventAttributes":{"homeTeamStartingPitcherName":"Jake Irvin","awayTeamStartingPitcherName":"Andrew Abbott"},"eventMetadata":{"participantMetadata":{"homeTeamStartingPitcherPlayerId":"107538","awayTeamStartingPitcherPlayerId":"162636","homeTeamStartingPitcherName":"Jake Irvin","awayTeamStartingPitcherName":"Andrew Abbott"},"mediaMetadata":{"BetRadarStats_Stats":{},"BetRadarV3_MatchTracker":{},"BetRadarV3_Scoreboard":{}}}},{"eventId":"30822893","displayGroupId":"7","eventGroupId":"84240","eventGroupName":"MLB","name":"STL Cardinals @ ATL Braves","nameIdentifier":"STL Cardinals @ ATL Braves","startDate":"2024-07-21T17:35:00.0000000Z","teamName1":"STL Cardinals","teamName2":"ATL Braves","teamShortName1":"STL","teamShortName2":"ATL","team1":{"teamId":29851,"name":"STL Cardinals","shortName":"STL"},"team2":{"teamId":29861,"name":"ATL Braves","shortName":"ATL"},"eventStatus":{"state":"NOT_STARTED","isClockDisabled":false,"minute":0,"second":0,"isClockRunning":false},"eventScorecard":{"scorecardComponentId":1},"mediaList":[{"mediaProviderName":"BetRadarStats","mediaId":"46682357","mediaTypeName":"Stats","metadata":{},"updatedAt":"2024-07-21T12:06:20.7592875Z"},{"mediaProviderName":"BetRadarV3","mediaId":"46682357","mediaTypeName":"MatchTracker","metadata":{"betRadarCoverage":"3"},"updatedAt":"2024-07-21T12:06:20.7592875Z"},{"mediaProviderName":"BetRadarV3","mediaId":"46682357","mediaTypeName":"Scoreboard","metadata":{"betRadarCoverage":"3"},"updatedAt":"2024-07-21T12:06:20.7592875Z"}],"liveBettingOffered":false,"liveBettingEnabled":false,"tags":["FeaturedSubcategory","Flashbet","MatchTracker","PrePack","ProgressiveParlayEligible","SGP","Scoreboard","SgpDynamicOdds","Stats","YourBetEligible"],"flashBetOfferCount":0,"eventAttributes":{"homeTeamStartingPitcherName":"Spencer Schwellenbach","awayTeamStartingPitcherName":"Miles Mikolas"},"eventMetadata":{"participantMetadata":{"homeTeamStartingPitcherPlayerId":"180195","awayTeamStartingPitcherPlayerId":"109195","homeTeamStartingPitcherName":"Spencer Schwellenbach","awayTeamStartingPitcherName":"Miles Mikolas"},"mediaMetadata":{"BetRadarStats_Stats":{},"BetRadarV3_MatchTracker":{},"BetRadarV3_Scoreboard":{}}}},{"eventId":"30822902","displayGroupId":"7","eventGroupId":"84240","eventGroupName":"MLB","name":"DET Tigers @ TOR Blue Jays","nameIdentifier":"DET Tigers @ TOR Blue Jays","startDate":"2024-07-21T17:37:00.0000000Z","teamName1":"DET Tigers","teamName2":"TOR Blue Jays","teamShortName1":"DET","teamShortName2":"TOR","team1":{"teamId":29871,"name":"DET Tigers","shortName":"DET"},"team2":{"teamId":29868,"name":"TOR Blue Jays","shortName":"TOR"},"eventStatus":{"state":"NOT_STARTED","isClockDisabled":false,"minute":0,"second":0,"isClockRunning":false},"eventScorecard":{"scorecardComponentId":1},"mediaList":[{"mediaProviderName":"BetRadarStats","mediaId":"46680447","mediaTypeName":"Stats","metadata":{},"updatedAt":"2024-07-21T11:03:16.2393640Z"},{"mediaProviderName":"BetRadarV3","mediaId":"46680447","mediaTypeName":"MatchTracker","metadata":{"betRadarCoverage":"3"},"updatedAt":"2024-07-21T11:03:16.2393640Z"},{"mediaProviderName":"BetRadarV3","mediaId":"46680447","mediaTypeName":"Scoreboard","metadata":{"betRadarCoverage":"3"},"updatedAt":"2024-07-21T11:03:16.2393640Z"}],"liveBettingOffered":false,"liveBettingEnabled":false,"tags":["FeaturedSubcategory","Flashbet","MatchTracker","PrePack","ProgressiveParlayEligible","SGP","Scoreboard","SgpDynamicOdds","Stats","YourBetEligible"],"flashBetOfferCount":0,"eventAttributes":{"homeTeamStartingPitcherName":"Kevin Gausman","awayTeamStartingPitcherName":"Keider Montero"},"eventMetadata":{"participantMetadata":{"homeTeamStartingPitcherPlayerId":"109288","awayTeamStartingPitcherPlayerId":"178740","homeTeamStartingPitcherName":"Kevin Gausman","awayTeamStartingPitcherName":"Keider Montero"},"mediaMetadata":{"BetRadarStats_Stats":{},"BetRadarV3_MatchTracker":{},"BetRadarV3_Scoreboard":{}}}},{"eventId":"30822939","displayGroupId":"7","eventGroupId":"84240","eventGroupName":"MLB","name":"NY Mets @ MIA Marlins","nameIdentifier":"NY Mets @ MIA Marlins","startDate":"2024-07-21T17:40:00.0000000Z","teamName1":"NY Mets","teamName2":"MIA Marlins","teamShortName1":"NYM","teamShortName2":"MIA","team1":{"teamId":29840,"name":"NY Mets","shortName":"NYM"},"team2":{"teamId":29953,"name":"MIA Marlins","shortName":"MIA"},"eventStatus":{"state":"NOT_STARTED","isClockDisabled":false,"minute":0,"second":0,"isClockRunning":false},"eventScorecard":{"scorecardComponentId":1},"mediaList":[{"mediaProviderName":"BetRadarStats","mediaId":"46683863","mediaTypeName":"Stats","metadata":{},"updatedAt":"2024-07-21T11:40:03.0010644Z"},{"mediaProviderName":"BetRadarV3","mediaId":"46683863","mediaTypeName":"MatchTracker","metadata":{"betRadarCoverage":"3"},"updatedAt":"2024-07-21T11:40:03.0010644Z"},{"mediaProviderName":"BetRadarV3","mediaId":"46683863","mediaTypeName":"Scoreboard","metadata":{"betRadarCoverage":"3"},"updatedAt":"2024-07-21T11:40:03.0010644Z"}],"liveBettingOffered":false,"liveBettingEnabled":false,"tags":["FeaturedSubcategory","Flashbet","MatchTracker","PrePack","ProgressiveParlayEligible","SGP","Scoreboard","SgpDynamicOdds","Stats","YourBetEligible"],"flashBetOfferCount":0,"eventAttributes":{"homeTeamStartingPitcherName":"Trevor Rogers","awayTeamStartingPitcherName":"Christian Scott"},"eventMetadata":{"participantMetadata":{"homeTeamStartingPitcherPlayerId":"108699","awayTeamStartingPitcherPlayerId":"179872","homeTeamStartingPitcherName":"Trevor Rogers","awayTeamStartingPitcherName":"Christian Scott"},"mediaMetadata":{"BetRadarStats_Stats":{},"BetRadarV3_MatchTracker":{},"BetRadarV3_Scoreboard":{}}}},{"eventId":"30822906","displayGroupId":"7","eventGroupId":"84240","eventGroupName":"MLB","name":"SD Padres @ CLE Guardians","nameIdentifier":"SD Padres @ CLE Guardians","startDate":"2024-07-21T17:40:00.0000000Z","teamName1":"SD Padres","teamName2":"CLE Guardians","teamShortName1":"SD","teamShortName2":"CLE","team1":{"teamId":29942,"name":"SD Padres","shortName":"SD"},"team2":{"teamId":29913,"name":"CLE Guardians","shortName":"CLE"},"eventStatus":{"state":"NOT_STARTED","isClockDisabled":false,"minute":0,"second":0,"isClockRunning":false},"eventScorecard":{"scorecardComponentId":1},"mediaList":[{"mediaProviderName":"BetRadarStats","mediaId":"46681185","mediaTypeName":"Stats","metadata":{},"updatedAt":"2024-07-21T12:08:00.8838572Z"},{"mediaProviderName":"BetRadarV3","mediaId":"46681185","mediaTypeName":"MatchTracker","metadata":{"betRadarCoverage":"3"},"updatedAt":"2024-07-21T12:08:00.8838572Z"},{"mediaProviderName":"BetRadarV3","mediaId":"46681185","mediaTypeName":"Scoreboard","metadata":{"betRadarCoverage":"3"},"updatedAt":"2024-07-21T12:08:00.8838572Z"}],"liveBettingOffered":false,"liveBettingEnabled":false,"tags":["FeaturedSubcategory","Flashbet","MatchTracker","PrePack","ProgressiveParlayEligible","SGP","Scoreboard","SgpDynamicOdds","Stats","YourBetEligible"],"flashBetOfferCount":0,"eventAttributes":{"homeTeamStartingPitcherName":"Ben Lively","awayTeamStartingPitcherName":"Michael King"},"eventMetadata":{"participantMetadata":{"homeTeamStartingPitcherPlayerId":"161975","awayTeamStartingPitcherPlayerId":"109764","homeTeamStartingPitcherName":"Ben Lively","awayTeamStartingPitcherName":"Michael King"},"mediaMetadata":{"BetRadarStats_Stats":{},"BetRadarV3_MatchTracker":{},"BetRadarV3_Scoreboard":{}}}},{"eventId":"30822910","displayGroupId":"7","eventGroupId":"84240","eventGroupName":"MLB","name":"CHI White Sox @ KC Royals","nameIdentifier":"CHI White Sox @ KC Royals","startDate":"2024-07-21T18:10:00.0000000Z","teamName1":"CHI White Sox","teamName2":"KC Royals","teamShortName1":"CWS","teamShortName2":"KC","team1":{"teamId":29970,"name":"CHI White Sox","shortName":"CWS"},"team2":{"teamId":29965,"name":"KC Royals","shortName":"KC"},"eventStatus":{"state":"NOT_STARTED","isClockDisabled":false,"minute":0,"second":0,"isClockRunning":false},"eventScorecard":{"scorecardComponentId":1},"mediaList":[{"mediaProviderName":"BetRadarStats","mediaId":"46680699","mediaTypeName":"Stats","metadata":{},"updatedAt":"2024-07-21T12:06:50.3788759Z"},{"mediaProviderName":"BetRadarV3","mediaId":"46680699","mediaTypeName":"MatchTracker","metadata":{"betRadarCoverage":"3"},"updatedAt":"2024-07-21T12:06:50.3788759Z"},{"mediaProviderName":"BetRadarV3","mediaId":"46680699","mediaTypeName":"Scoreboard","metadata":{"betRadarCoverage":"3"},"updatedAt":"2024-07-21T12:06:50.3788759Z"}],"liveBettingOffered":false,"liveBettingEnabled":false,"tags":["FeaturedSubcategory","Flashbet","MatchTracker","PrePack","ProgressiveParlayEligible","SGP","Scoreboard","SgpDynamicOdds","Stats","YourBetEligible"],"flashBetOfferCount":0,"eventAttributes":{"homeTeamStartingPitcherName":"Seth Lugo","awayTeamStartingPitcherName":"Drew Thorpe"},"eventMetadata":{"participantMetadata":{"homeTeamStartingPitcherPlayerId":"108337","awayTeamStartingPitcherPlayerId":"156916","homeTeamStartingPitcherName":"Seth Lugo","awayTeamStartingPitcherName":"Drew Thorpe"},"mediaMetadata":{"BetRadarStats_Stats":{},"BetRadarV3_MatchTracker":{},"BetRadarV3_Scoreboard":{}}}},{"eventId":"30822927","displayGroupId":"7","eventGroupId":"84240","eventGroupName":"MLB","name":"ARI Diamondbacks @ CHI Cubs","nameIdentifier":"ARI Diamondbacks @ CHI Cubs","startDate":"2024-07-21T18:20:00.0000000Z","teamName1":"ARI Diamondbacks","teamName2":"CHI Cubs","teamShortName1":"ARI","teamShortName2":"CHC","team1":{"teamId":29934,"name":"ARI Diamondbacks","shortName":"ARI"},"team2":{"teamId":29894,"name":"CHI Cubs","shortName":"CHC"},"eventStatus":{"state":"NOT_STARTED","isClockDisabled":false,"minute":0,"second":0,"isClockRunning":false},"eventScorecard":{"scorecardComponentId":1},"mediaList":[{"mediaProviderName":"BetRadarStats","mediaId":"46680563","mediaTypeName":"Stats","metadata":{},"updatedAt":"2024-07-21T12:09:40.7627807Z"},{"mediaProviderName":"BetRadarV3","mediaId":"46680563","mediaTypeName":"MatchTracker","metadata":{"betRadarCoverage":"3"},"updatedAt":"2024-07-21T12:09:40.7627807Z"},{"mediaProviderName":"BetRadarV3","mediaId":"46680563","mediaTypeName":"Scoreboard","metadata":{"betRadarCoverage":"3"},"updatedAt":"2024-07-21T12:09:40.7627807Z"}],"liveBettingOffered":false,"liveBettingEnabled":false,"tags":["FeaturedSubcategory","Flashbet","MatchTracker","PrePack","ProgressiveParlayEligible","SGP","Scoreboard","SgpDynamicOdds","Stats","YourBetEligible"],"flashBetOfferCount":0,"eventAttributes":{"homeTeamStartingPitcherName":"Shota Imanaga","awayTeamStartingPitcherName":"Brandon Pfaadt"},"eventMetadata":{"participantMetadata":{"homeTeamStartingPitcherPlayerId":"178160","awayTeamStartingPitcherPlayerId":"161929","homeTeamStartingPitcherName":"Shota Imanaga","awayTeamStartingPitcherName":"Brandon Pfaadt"},"mediaMetadata":{"BetRadarStats_Stats":{},"BetRadarV3_MatchTracker":{},"BetRadarV3_Scoreboard":{}}}},{"eventId":"30822928","displayGroupId":"7","eventGroupId":"84240","eventGroupName":"MLB","name":"BAL Orioles @ TEX Rangers","nameIdentifier":"BAL Orioles @ TEX Rangers","startDate":"2024-07-21T18:35:00.0000000Z","teamName1":"BAL Orioles","teamName2":"TEX Rangers","teamShortName1":"BAL","teamShortName2":"TEX","team1":{"teamId":29829,"name":"BAL Orioles","shortName":"BAL"},"team2":{"teamId":29891,"name":"TEX Rangers","shortName":"TEX"},"eventStatus":{"state":"NOT_STARTED","isClockDisabled":false,"minute":0,"second":0,"isClockRunning":false},"eventScorecard":{"scorecardComponentId":1},"mediaList":[{"mediaProviderName":"BetRadarStats","mediaId":"46684765","mediaTypeName":"Stats","metadata":{},"updatedAt":"2024-07-21T12:11:45.3530722Z"},{"mediaProviderName":"BetRadarV3","mediaId":"46684765","mediaTypeName":"MatchTracker","metadata":{"betRadarCoverage":"3"},"updatedAt":"2024-07-21T12:11:45.3530722Z"},{"mediaProviderName":"BetRadarV3","mediaId":"46684765","mediaTypeName":"Scoreboard","metadata":{"betRadarCoverage":"3"},"updatedAt":"2024-07-21T12:11:45.3530722Z"}],"liveBettingOffered":false,"liveBettingEnabled":false,"tags":["FeaturedSubcategory","Flashbet","MatchTracker","PrePack","ProgressiveParlayEligible","SGP","Scoreboard","SgpDynamicOdds","Stats","YourBetEligible"],"flashBetOfferCount":0,"eventAttributes":{"homeTeamStartingPitcherName":"Andrew Heaney","awayTeamStartingPitcherName":"Dean Kremer"},"eventMetadata":{"participantMetadata":{"homeTeamStartingPitcherPlayerId":"109046","awayTeamStartingPitcherPlayerId":"105913","homeTeamStartingPitcherName":"Andrew Heaney","awayTeamStartingPitcherName":"Dean Kremer"},"mediaMetadata":{"BetRadarStats_Stats":{},"BetRadarV3_MatchTracker":{},"BetRadarV3_Scoreboard":{}}}},{"eventId":"30822931","displayGroupId":"7","eventGroupId":"84240","eventGroupName":"MLB","name":"SF Giants @ COL Rockies","nameIdentifier":"SF Giants @ COL Rockies","startDate":"2024-07-21T19:10:00.0000000Z","teamName1":"SF Giants","teamName2":"COL Rockies","teamShortName1":"SFG","teamShortName2":"COL","team1":{"teamId":29945,"name":"SF Giants","shortName":"SFG"},"team2":{"teamId":29957,"name":"COL Rockies","shortName":"COL"},"eventStatus":{"state":"NOT_STARTED","isClockDisabled":false,"minute":0,"second":0,"isClockRunning":false},"eventScorecard":{"scorecardComponentId":1},"mediaList":[{"mediaProviderName":"BetRadarStats","mediaId":"46684547","mediaTypeName":"Stats","metadata":{},"updatedAt":"2024-07-21T11:55:39.1896883Z"},{"mediaProviderName":"BetRadarV3","mediaId":"46684547","mediaTypeName":"MatchTracker","metadata":{"betRadarCoverage":"3"},"updatedAt":"2024-07-21T11:55:39.1896883Z"},{"mediaProviderName":"BetRadarV3","mediaId":"46684547","mediaTypeName":"Scoreboard","metadata":{"betRadarCoverage":"3"},"updatedAt":"2024-07-21T11:55:39.1896883Z"}],"liveBettingOffered":false,"liveBettingEnabled":false,"tags":["FeaturedSubcategory","Flashbet","MatchTracker","PrePack","ProgressiveParlayEligible","SGP","Scoreboard","SgpDynamicOdds","Stats","YourBetEligible"],"flashBetOfferCount":0,"eventAttributes":{"homeTeamStartingPitcherName":"Austin Gomber","awayTeamStartingPitcherName":"Hayden Birdsong"},"eventMetadata":{"participantMetadata":{"homeTeamStartingPitcherPlayerId":"109742","awayTeamStartingPitcherPlayerId":"181037","homeTeamStartingPitcherName":"Austin Gomber","awayTeamStartingPitcherName":"Hayden Birdsong"},"mediaMetadata":{"BetRadarStats_Stats":{},"BetRadarV3_MatchTracker":{},"BetRadarV3_Scoreboard":{}}}},{"eventId":"30822933","displayGroupId":"7","eventGroupId":"84240","eventGroupName":"MLB","name":"LA Angels @ OAK Athletics","nameIdentifier":"LA Angels @ OAK Athletics","startDate":"2024-07-21T20:07:00.0000000Z","teamName1":"LA Angels","teamName2":"OAK Athletics","teamShortName1":"LAA","teamShortName2":"OAK","team1":{"teamId":29901,"name":"LA Angels","shortName":"LAA"},"team2":{"teamId":29811,"name":"OAK Athletics","shortName":"OAK"},"eventStatus":{"state":"NOT_STARTED","isClockDisabled":false,"minute":0,"second":0,"isClockRunning":false},"eventScorecard":{"scorecardComponentId":1},"mediaList":[{"mediaProviderName":"BetRadarStats","mediaId":"46681049","mediaTypeName":"Stats","metadata":{},"updatedAt":"2024-07-21T11:19:05.4699727Z"},{"mediaProviderName":"BetRadarV3","mediaId":"46681049","mediaTypeName":"MatchTracker","metadata":{"betRadarCoverage":"3"},"updatedAt":"2024-07-21T11:19:05.4699727Z"},{"mediaProviderName":"BetRadarV3","mediaId":"46681049","mediaTypeName":"Scoreboard","metadata":{"betRadarCoverage":"3"},"updatedAt":"2024-07-21T11:19:05.4699727Z"}],"liveBettingOffered":false,"liveBettingEnabled":false,"tags":["FeaturedSubcategory","Flashbet","MatchTracker","PrePack","ProgressiveParlayEligible","SGP","Scoreboard","SgpDynamicOdds","Stats","YourBetEligible"],"flashBetOfferCount":0,"eventAttributes":{"homeTeamStartingPitcherName":"Joey Estes","awayTeamStartingPitcherName":"Carson Fulmer"},"eventMetadata":{"participantMetadata":{"homeTeamStartingPitcherPlayerId":"175971","awayTeamStartingPitcherPlayerId":"107999","homeTeamStartingPitcherName":"Joey Estes","awayTeamStartingPitcherName":"Carson Fulmer"},"mediaMetadata":{"BetRadarStats_Stats":{},"BetRadarV3_MatchTracker":{},"BetRadarV3_Scoreboard":{}}}},{"eventId":"30822940","displayGroupId":"7","eventGroupId":"84240","eventGroupName":"MLB","name":"HOU Astros @ SEA Mariners","nameIdentifier":"HOU Astros @ SEA Mariners","startDate":"2024-07-21T20:10:00.0000000Z","teamName1":"HOU Astros","teamName2":"SEA Mariners","teamShortName1":"HOU","teamShortName2":"SEA","team1":{"teamId":29882,"name":"HOU Astros","shortName":"HOU"},"team2":{"teamId":29815,"name":"SEA Mariners","shortName":"SEA"},"eventStatus":{"state":"NOT_STARTED","isClockDisabled":false,"minute":0,"second":0,"isClockRunning":false},"eventScorecard":{"scorecardComponentId":1},"mediaList":[{"mediaProviderName":"BetRadarStats","mediaId":"46682519","mediaTypeName":"Stats","metadata":{},"updatedAt":"2024-07-21T11:55:39.1924761Z"},{"mediaProviderName":"BetRadarV3","mediaId":"46682519","mediaTypeName":"MatchTracker","metadata":{"betRadarCoverage":"3"},"updatedAt":"2024-07-21T11:55:39.1924761Z"},{"mediaProviderName":"BetRadarV3","mediaId":"46682519","mediaTypeName":"Scoreboard","metadata":{"betRadarCoverage":"3"},"updatedAt":"2024-07-21T11:55:39.1924761Z"}],"liveBettingOffered":false,"liveBettingEnabled":false,"tags":["FeaturedSubcategory","Flashbet","MatchTracker","PrePack","ProgressiveParlayEligible","SGP","Scoreboard","SgpDynamicOdds","Stats","YourBetEligible"],"flashBetOfferCount":0,"eventAttributes":{"homeTeamStartingPitcherName":"Bryan Woo","awayTeamStartingPitcherName":"Ronel Blanco"},"eventMetadata":{"participantMetadata":{"homeTeamStartingPitcherPlayerId":"162619","awayTeamStartingPitcherPlayerId":"152292","homeTeamStartingPitcherName":"Bryan Woo","awayTeamStartingPitcherName":"Ronel Blanco"},"mediaMetadata":{"BetRadarStats_Stats":{},"BetRadarV3_MatchTracker":{},"BetRadarV3_Scoreboard":{}}}},{"eventId":"30822943","displayGroupId":"7","eventGroupId":"84240","eventGroupName":"MLB","name":"BOS Red Sox @ LA Dodgers","nameIdentifier":"BOS Red Sox @ LA Dodgers","startDate":"2024-07-21T23:10:00.0000000Z","teamName1":"BOS Red Sox","teamName2":"LA Dodgers","teamShortName1":"BOS","teamShortName2":"LAD","team1":{"teamId":29976,"name":"BOS Red Sox","shortName":"BOS"},"team2":{"teamId":29931,"name":"LA Dodgers","shortName":"LAD"},"eventStatus":{"state":"NOT_STARTED","isClockDisabled":false,"minute":0,"second":0,"isClockRunning":false},"eventScorecard":{"scorecardComponentId":1},"mediaList":[{"mediaProviderName":"BetRadarStats","mediaId":"46680903","mediaTypeName":"Stats","metadata":{},"updatedAt":"2024-07-21T11:06:20.4158597Z"},{"mediaProviderName":"BetRadarV3","mediaId":"46680903","mediaTypeName":"MatchTracker","metadata":{"betRadarCoverage":"3"},"updatedAt":"2024-07-21T11:06:20.4158597Z"},{"mediaProviderName":"BetRadarV3","mediaId":"46680903","mediaTypeName":"Scoreboard","metadata":{"betRadarCoverage":"3"},"updatedAt":"2024-07-21T11:06:20.4158597Z"}],"liveBettingOffered":false,"liveBettingEnabled":false,"tags":["FeaturedSubcategory","Flashbet","MatchTracker","PrePack","ProgressiveParlayEligible","SGP","Scoreboard","SgpDynamicOdds","Stats","YourBetEligible"],"flashBetOfferCount":0,"eventAttributes":{"homeTeamStartingPitcherName":"James Paxton","awayTeamStartingPitcherName":"Kutter Crawford"},"eventMetadata":{"participantMetadata":{"homeTeamStartingPitcherPlayerId":"109348","awayTeamStartingPitcherPlayerId":"106025","homeTeamStartingPitcherName":"James Paxton","awayTeamStartingPitcherName":"Kutter Crawford"},"mediaMetadata":{"BetRadarStats_Stats":{},"BetRadarV3_MatchTracker":{},"BetRadarV3_Scoreboard":{}}}}],"tags":["FeaturedSubcategory","Flashbet","MatchTracker","PrePack","ProgressiveParlayEligible","SGP","Scoreboard","SgpDynamicOdds","Stats","YourBetEligible"],"nameIdentifier":"MLB"}}